{
"meta":{"test_sets":[],"test_metrics":[],"learn_metrics":[{"best_value":"Min","name":"MultiClass"}],"launch_mode":"Train","parameters":"","iteration_count":1000,"learn_sets":["learn"],"name":"experiment"},
"iterations":[
{"learn":[1.434826181],"iteration":0,"passed_time":0.003066708156,"remaining_time":3.063641448},
{"learn":[1.305764654],"iteration":1,"passed_time":0.005968649582,"remaining_time":2.978356141},
{"learn":[1.200576441],"iteration":2,"passed_time":0.00887555738,"remaining_time":2.949643569},
{"learn":[1.116253864],"iteration":3,"passed_time":0.01161697674,"remaining_time":2.892627209},
{"learn":[1.042161731],"iteration":4,"passed_time":0.01406144948,"remaining_time":2.798228447},
{"learn":[0.9808559107],"iteration":5,"passed_time":0.01614498418,"remaining_time":2.674685712},
{"learn":[0.9277764216],"iteration":6,"passed_time":0.01828608414,"remaining_time":2.59401165},
{"learn":[0.8843480993],"iteration":7,"passed_time":0.02035529113,"remaining_time":2.524056101},
{"learn":[0.851989871],"iteration":8,"passed_time":0.02230564448,"remaining_time":2.456099298},
{"learn":[0.8189192495],"iteration":9,"passed_time":0.02408712258,"remaining_time":2.384625136},
{"learn":[0.7864068765],"iteration":10,"passed_time":0.02567481249,"remaining_time":2.30839905},
{"learn":[0.7566755336],"iteration":11,"passed_time":0.02717342987,"remaining_time":2.237279059},
{"learn":[0.7280183707],"iteration":12,"passed_time":0.02854767739,"remaining_time":2.167427506},
{"learn":[0.705585522],"iteration":13,"passed_time":0.02993639249,"remaining_time":2.108377357},
{"learn":[0.6854193379],"iteration":14,"passed_time":0.03133806183,"remaining_time":2.05786606},
{"learn":[0.6665074463],"iteration":15,"passed_time":0.03271840739,"remaining_time":2.012182054},
{"learn":[0.6497707839],"iteration":16,"passed_time":0.03417719855,"remaining_time":1.976246246},
{"learn":[0.6344877984],"iteration":17,"passed_time":0.03555278309,"remaining_time":1.939601833},
{"learn":[0.6206500466],"iteration":18,"passed_time":0.03691121039,"remaining_time":1.905784074},
{"learn":[0.6069543863],"iteration":19,"passed_time":0.03829851929,"remaining_time":1.876627445},
{"learn":[0.5948186227],"iteration":20,"passed_time":0.03968384982,"remaining_time":1.850023284},
{"learn":[0.5822318834],"iteration":21,"passed_time":0.04105763679,"remaining_time":1.825198581},
{"learn":[0.570901447],"iteration":22,"passed_time":0.04244568599,"remaining_time":1.803018922},
{"learn":[0.5581465068],"iteration":23,"passed_time":0.04376899677,"remaining_time":1.779939202},
{"learn":[0.5529600252],"iteration":24,"passed_time":0.04510227452,"remaining_time":1.758988706},
{"learn":[0.5458455433],"iteration":25,"passed_time":0.04641733702,"remaining_time":1.738864856},
{"learn":[0.5358234886],"iteration":26,"passed_time":0.0478673591,"remaining_time":1.724997793},
{"learn":[0.5299916615],"iteration":27,"passed_time":0.04922558701,"remaining_time":1.708831092},
{"learn":[0.5232202067],"iteration":28,"passed_time":0.05058726645,"remaining_time":1.693801232},
{"learn":[0.511260904],"iteration":29,"passed_time":0.05214814911,"remaining_time":1.686123488},
{"learn":[0.505622985],"iteration":30,"passed_time":0.05370144047,"remaining_time":1.678603091},
{"learn":[0.4996296986],"iteration":31,"passed_time":0.05510491928,"remaining_time":1.666923808},
{"learn":[0.4917332308],"iteration":32,"passed_time":0.0565551162,"remaining_time":1.657236284},
{"learn":[0.4827384231],"iteration":33,"passed_time":0.0579671089,"remaining_time":1.646947859},
{"learn":[0.4775754352],"iteration":34,"passed_time":0.05927399977,"remaining_time":1.634268851},
{"learn":[0.4704874911],"iteration":35,"passed_time":0.06062542505,"remaining_time":1.62341416},
{"learn":[0.4661867042],"iteration":36,"passed_time":0.06198129365,"remaining_time":1.613188805},
{"learn":[0.4631356271],"iteration":37,"passed_time":0.06339729441,"remaining_time":1.604952558},
{"learn":[0.4571474251],"iteration":38,"passed_time":0.06485317346,"remaining_time":1.59804871},
{"learn":[0.4509087361],"iteration":39,"passed_time":0.06661753153,"remaining_time":1.598820757},
{"learn":[0.4481487079],"iteration":40,"passed_time":0.06799756311,"remaining_time":1.590479586},
{"learn":[0.4437294691],"iteration":41,"passed_time":0.06952519451,"remaining_time":1.58583658},
{"learn":[0.4400247938],"iteration":42,"passed_time":0.07091414175,"remaining_time":1.578251946},
{"learn":[0.4341976889],"iteration":43,"passed_time":0.07240467827,"remaining_time":1.573156191},
{"learn":[0.4314292424],"iteration":44,"passed_time":0.07408233874,"remaining_time":1.572191855},
{"learn":[0.4295205465],"iteration":45,"passed_time":0.07556986046,"remaining_time":1.567253193},
{"learn":[0.4248294889],"iteration":46,"passed_time":0.07749880223,"remaining_time":1.571411884},
{"learn":[0.4221085328],"iteration":47,"passed_time":0.07883761255,"remaining_time":1.563612649},
{"learn":[0.4206255363],"iteration":48,"passed_time":0.08026275665,"remaining_time":1.557752685},
{"learn":[0.4145529989],"iteration":49,"passed_time":0.08179821669,"remaining_time":1.554166117},
{"learn":[0.4087441102],"iteration":50,"passed_time":0.08335298122,"remaining_time":1.5510192},
{"learn":[0.4058900592],"iteration":51,"passed_time":0.08472309866,"remaining_time":1.54456726},
{"learn":[0.4016426498],"iteration":52,"passed_time":0.08609593328,"remaining_time":1.538355638},
{"learn":[0.3966582651],"iteration":53,"passed_time":0.08742940745,"remaining_time":1.531633693},
{"learn":[0.3939393334],"iteration":54,"passed_time":0.08881809725,"remaining_time":1.526056398},
{"learn":[0.3923698586],"iteration":55,"passed_time":0.09030411158,"remaining_time":1.522269309},
{"learn":[0.39043816],"iteration":56,"passed_time":0.09164610856,"remaining_time":1.516180357},
{"learn":[0.3850998554],"iteration":57,"passed_time":0.09297522348,"remaining_time":1.510045871},
{"learn":[0.382992818],"iteration":58,"passed_time":0.09462651569,"remaining_time":1.509212733},
{"learn":[0.3812186885],"iteration":59,"passed_time":0.09613884769,"remaining_time":1.50617528},
{"learn":[0.3756158636],"iteration":60,"passed_time":0.09758580141,"remaining_time":1.502181435},
{"learn":[0.3734094924],"iteration":61,"passed_time":0.09918301633,"remaining_time":1.500543054},
{"learn":[0.3722024901],"iteration":62,"passed_time":0.10088556,"remaining_time":1.500472535},
{"learn":[0.3699478427],"iteration":63,"passed_time":0.1022506195,"remaining_time":1.495415311},
{"learn":[0.3672417076],"iteration":64,"passed_time":0.1037025396,"remaining_time":1.491721147},
{"learn":[0.3644528794],"iteration":65,"passed_time":0.1051663351,"remaining_time":1.488262985},
{"learn":[0.3616040265],"iteration":66,"passed_time":0.10662563,"remaining_time":1.484801683},
{"learn":[0.3585913452],"iteration":67,"passed_time":0.1079679529,"remaining_time":1.47979606},
{"learn":[0.3547629801],"iteration":68,"passed_time":0.1093717159,"remaining_time":1.475725616},
{"learn":[0.3531373347],"iteration":69,"passed_time":0.1107094652,"remaining_time":1.470854324},
{"learn":[0.3506262735],"iteration":70,"passed_time":0.1120855654,"remaining_time":1.466584369},
{"learn":[0.3472079343],"iteration":71,"passed_time":0.1135692621,"remaining_time":1.4637816},
{"learn":[0.3452269875],"iteration":72,"passed_time":0.1149437551,"remaining_time":1.459628233},
{"learn":[0.3439476911],"iteration":73,"passed_time":0.1163219512,"remaining_time":1.455596308},
{"learn":[0.3417448199],"iteration":74,"passed_time":0.1176429227,"remaining_time":1.45092938},
{"learn":[0.3392051928],"iteration":75,"passed_time":0.119028199,"remaining_time":1.447132314},
{"learn":[0.3376007911],"iteration":76,"passed_time":0.1204690725,"remaining_time":1.444064337},
{"learn":[0.3349043653],"iteration":77,"passed_time":0.1219842162,"remaining_time":1.441915991},
{"learn":[0.333510669],"iteration":78,"passed_time":0.1234296424,"remaining_time":1.438970894},
{"learn":[0.3314118773],"iteration":79,"passed_time":0.1247962622,"remaining_time":1.435157015},
{"learn":[0.3287986154],"iteration":80,"passed_time":0.1261910232,"remaining_time":1.431722844},
{"learn":[0.3274219953],"iteration":81,"passed_time":0.1277868111,"remaining_time":1.430588934},
{"learn":[0.3261198403],"iteration":82,"passed_time":0.1292742793,"remaining_time":1.428247158},
{"learn":[0.3239146845],"iteration":83,"passed_time":0.1307614617,"remaining_time":1.425922606},
{"learn":[0.3222592361],"iteration":84,"passed_time":0.1322073068,"remaining_time":1.423172774},
{"learn":[0.3207434742],"iteration":85,"passed_time":0.133667182,"remaining_time":1.420602377},
{"learn":[0.3197405635],"iteration":86,"passed_time":0.1351932525,"remaining_time":1.418752178},
{"learn":[0.3183293196],"iteration":87,"passed_time":0.1384806647,"remaining_time":1.435163252},
{"learn":[0.3172928313],"iteration":88,"passed_time":0.1400373548,"remaining_time":1.43341607},
{"learn":[0.3159426935],"iteration":89,"passed_time":0.1414396104,"remaining_time":1.430111616},
{"learn":[0.3151110376],"iteration":90,"passed_time":0.1437406097,"remaining_time":1.43582653},
{"learn":[0.3142409987],"iteration":91,"passed_time":0.1451281321,"remaining_time":1.432351565},
{"learn":[0.312333327],"iteration":92,"passed_time":0.1467790932,"remaining_time":1.431490726},
{"learn":[0.3106536171],"iteration":93,"passed_time":0.1481732628,"remaining_time":1.428138043},
{"learn":[0.3082296859],"iteration":94,"passed_time":0.1495926526,"remaining_time":1.425066848},
{"learn":[0.3062483476],"iteration":95,"passed_time":0.1509573453,"remaining_time":1.421515002},
{"learn":[0.3043591723],"iteration":96,"passed_time":0.1522922718,"remaining_time":1.417731149},
{"learn":[0.3017998669],"iteration":97,"passed_time":0.1536136653,"remaining_time":1.413872715},
{"learn":[0.3009571543],"iteration":98,"passed_time":0.1549713344,"remaining_time":1.41039568},
{"learn":[0.299962653],"iteration":99,"passed_time":0.1563645531,"remaining_time":1.407280978},
{"learn":[0.2985724904],"iteration":100,"passed_time":0.1576866645,"remaining_time":1.403567439},
{"learn":[0.2967255907],"iteration":101,"passed_time":0.1590568139,"remaining_time":1.400323715},
{"learn":[0.2959027456],"iteration":102,"passed_time":0.1604643298,"remaining_time":1.397441785},
{"learn":[0.2928907358],"iteration":103,"passed_time":0.1618484424,"remaining_time":1.394386581},
{"learn":[0.2912570799],"iteration":104,"passed_time":0.1633486773,"remaining_time":1.392353011},
{"learn":[0.2906704798],"iteration":105,"passed_time":0.1650489509,"remaining_time":1.392016624},
{"learn":[0.2886110218],"iteration":106,"passed_time":0.1666486368,"remaining_time":1.390815258},
{"learn":[0.2851513418],"iteration":107,"passed_time":0.1680895892,"remaining_time":1.388295496},
{"learn":[0.2832261098],"iteration":108,"passed_time":0.1696887006,"remaining_time":1.387088369},
{"learn":[0.2825880749],"iteration":109,"passed_time":0.1710886356,"remaining_time":1.384262597},
{"learn":[0.2814295725],"iteration":110,"passed_time":0.1726307443,"remaining_time":1.382601186},
{"learn":[0.2793571414],"iteration":111,"passed_time":0.1740925391,"remaining_time":1.380305131},
{"learn":[0.278243307],"iteration":112,"passed_time":0.1754469107,"remaining_time":1.377180618},
{"learn":[0.2766733651],"iteration":113,"passed_time":0.1769007355,"remaining_time":1.374860102},
{"learn":[0.274368872],"iteration":114,"passed_time":0.178308677,"remaining_time":1.372201557},
{"learn":[0.2712490723],"iteration":115,"passed_time":0.1797366863,"remaining_time":1.369717506},
{"learn":[0.2705048632],"iteration":116,"passed_time":0.1810656844,"remaining_time":1.366504268},
{"learn":[0.2666349358],"iteration":117,"passed_time":0.1825043035,"remaining_time":1.364142337},
{"learn":[0.2648228572],"iteration":118,"passed_time":0.183899732,"remaining_time":1.361476167},
{"learn":[0.264454913],"iteration":119,"passed_time":0.1852221113,"remaining_time":1.358295483},
{"learn":[0.263005808],"iteration":120,"passed_time":0.1865418648,"remaining_time":1.35512644},
{"learn":[0.2624444336],"iteration":121,"passed_time":0.1878766634,"remaining_time":1.352095987},
{"learn":[0.2602723027],"iteration":122,"passed_time":0.189206256,"remaining_time":1.349055988},
{"learn":[0.2589319502],"iteration":123,"passed_time":0.1905931795,"remaining_time":1.34644859},
{"learn":[0.2582012969],"iteration":124,"passed_time":0.1919974648,"remaining_time":1.343982253},
{"learn":[0.2563972605],"iteration":125,"passed_time":0.1933206736,"remaining_time":1.340970387},
{"learn":[0.2554461677],"iteration":126,"passed_time":0.1947374645,"remaining_time":1.338628398},
{"learn":[0.2549186728],"iteration":127,"passed_time":0.1963562592,"remaining_time":1.337677016},
{"learn":[0.2533768778],"iteration":128,"passed_time":0.1977953999,"remaining_time":1.335502274},
{"learn":[0.2517942297],"iteration":129,"passed_time":0.1991526881,"remaining_time":1.332791066},
{"learn":[0.2506008891],"iteration":130,"passed_time":0.200484134,"remaining_time":1.329929103},
{"learn":[0.2497842122],"iteration":131,"passed_time":0.2018611687,"remaining_time":1.327390109},
{"learn":[0.2491407913],"iteration":132,"passed_time":0.2032039893,"remaining_time":1.324645554},
{"learn":[0.2482965186],"iteration":133,"passed_time":0.2045733292,"remaining_time":1.322093307},
{"learn":[0.2472394982],"iteration":134,"passed_time":0.2059133516,"remaining_time":1.319370734},
{"learn":[0.2464443354],"iteration":135,"passed_time":0.2072588819,"remaining_time":1.316703485},
{"learn":[0.2448313045],"iteration":136,"passed_time":0.2085877647,"remaining_time":1.313950664},
{"learn":[0.2426848935],"iteration":137,"passed_time":0.2099561092,"remaining_time":1.311464972},
{"learn":[0.2420594226],"iteration":138,"passed_time":0.2120090674,"remaining_time":1.313236022},
{"learn":[0.240978585],"iteration":139,"passed_time":0.2134449448,"remaining_time":1.311161804},
{"learn":[0.2402550215],"iteration":140,"passed_time":0.2148072388,"remaining_time":1.308648355},
{"learn":[0.2392120868],"iteration":141,"passed_time":0.2161495899,"remaining_time":1.306030621},
{"learn":[0.23841075],"iteration":142,"passed_time":0.2174587754,"remaining_time":1.303231961},
{"learn":[0.2367258329],"iteration":143,"passed_time":0.2187957851,"remaining_time":1.300619389},
{"learn":[0.2351038445],"iteration":144,"passed_time":0.2202509723,"remaining_time":1.29872125},
{"learn":[0.2339586492],"iteration":145,"passed_time":0.2215594754,"remaining_time":1.295971178},
{"learn":[0.2324987858],"iteration":146,"passed_time":0.222891597,"remaining_time":1.29337777},
{"learn":[0.2310083628],"iteration":147,"passed_time":0.2242650551,"remaining_time":1.291039371},
{"learn":[0.2299805505],"iteration":148,"passed_time":0.225642769,"remaining_time":1.288738231},
{"learn":[0.2285197568],"iteration":149,"passed_time":0.2270318814,"remaining_time":1.286513995},
{"learn":[0.2276367122],"iteration":150,"passed_time":0.2285886757,"remaining_time":1.285243613},
{"learn":[0.2270054481],"iteration":151,"passed_time":0.2300763373,"remaining_time":1.283583776},
{"learn":[0.2265756444],"iteration":152,"passed_time":0.2314572453,"remaining_time":1.281335208},
{"learn":[0.2258407816],"iteration":153,"passed_time":0.2328148534,"remaining_time":1.278969909},
{"learn":[0.2253641493],"iteration":154,"passed_time":0.2341424386,"remaining_time":1.27645394},
{"learn":[0.224005897],"iteration":155,"passed_time":0.23546319,"remaining_time":1.273916233},
{"learn":[0.2235143415],"iteration":156,"passed_time":0.2368591645,"remaining_time":1.271797934},
{"learn":[0.2232661494],"iteration":157,"passed_time":0.2381677801,"remaining_time":1.269223233},
{"learn":[0.2220991769],"iteration":158,"passed_time":0.2395146154,"remaining_time":1.266866614},
{"learn":[0.2216007351],"iteration":159,"passed_time":0.2408596108,"remaining_time":1.264512957},
{"learn":[0.2209677276],"iteration":160,"passed_time":0.2421961229,"remaining_time":1.262127622},
{"learn":[0.2202858406],"iteration":161,"passed_time":0.2436319913,"remaining_time":1.26026919},
{"learn":[0.2196626477],"iteration":162,"passed_time":0.2449577708,"remaining_time":1.257850639},
{"learn":[0.2174189193],"iteration":163,"passed_time":0.2462936549,"remaining_time":1.255496924},
{"learn":[0.2168439808],"iteration":164,"passed_time":0.2476055813,"remaining_time":1.253034305},
{"learn":[0.2158024306],"iteration":165,"passed_time":0.2492139708,"remaining_time":1.25207501},
{"learn":[0.2152622063],"iteration":166,"passed_time":0.2507199056,"remaining_time":1.250596895},
{"learn":[0.2135992304],"iteration":167,"passed_time":0.252162073,"remaining_time":1.248802647},
{"learn":[0.2129530725],"iteration":168,"passed_time":0.2535150727,"remaining_time":1.246574115},
{"learn":[0.2126850211],"iteration":169,"passed_time":0.2548980811,"remaining_time":1.244502396},
{"learn":[0.2117088819],"iteration":170,"passed_time":0.2562671591,"remaining_time":1.242371198},
{"learn":[0.2113221792],"iteration":171,"passed_time":0.257589987,"remaining_time":1.240026217},
{"learn":[0.2109262827],"iteration":172,"passed_time":0.2589481256,"remaining_time":1.237861849},
{"learn":[0.2105977282],"iteration":173,"passed_time":0.2603988032,"remaining_time":1.236146043},
{"learn":[0.2101381542],"iteration":174,"passed_time":0.2618549866,"remaining_time":1.234459222},
{"learn":[0.2092581569],"iteration":175,"passed_time":0.2633975848,"remaining_time":1.233179602},
{"learn":[0.2079927005],"iteration":176,"passed_time":0.2647746566,"remaining_time":1.231127358},
{"learn":[0.2073841459],"iteration":177,"passed_time":0.2662265715,"remaining_time":1.229428325},
{"learn":[0.2065872392],"iteration":178,"passed_time":0.2675555056,"remaining_time":1.22716799},
{"learn":[0.2062242679],"iteration":179,"passed_time":0.2688982236,"remaining_time":1.224980796},
{"learn":[0.2049335184],"iteration":180,"passed_time":0.2703359425,"remaining_time":1.2232328},
{"learn":[0.2045778059],"iteration":181,"passed_time":0.2716914822,"remaining_time":1.22111886},
{"learn":[0.2044396393],"iteration":182,"passed_time":0.273013976,"remaining_time":1.218865674},
{"learn":[0.2035600876],"iteration":183,"passed_time":0.274341815,"remaining_time":1.21664631},
{"learn":[0.2030289127],"iteration":184,"passed_time":0.2756833648,"remaining_time":1.214496985},
{"learn":[0.2025817536],"iteration":185,"passed_time":0.2771611026,"remaining_time":1.212952352},
{"learn":[0.2019622572],"iteration":186,"passed_time":0.2785360405,"remaining_time":1.210961502},
{"learn":[0.2013260271],"iteration":187,"passed_time":0.2798836386,"remaining_time":1.20885912},
{"learn":[0.2007432687],"iteration":188,"passed_time":0.2812306071,"remaining_time":1.206762023},
{"learn":[0.1993387002],"iteration":189,"passed_time":0.2825963958,"remaining_time":1.204753056},
{"learn":[0.19913917],"iteration":190,"passed_time":0.2839496856,"remaining_time":1.202697883},
{"learn":[0.1984453798],"iteration":191,"passed_time":0.2852826896,"remaining_time":1.200564652},
{"learn":[0.1978377113],"iteration":192,"passed_time":0.2865917188,"remaining_time":1.198339467},
{"learn":[0.1974358846],"iteration":193,"passed_time":0.2879312761,"remaining_time":1.196250559},
{"learn":[0.1973005412],"iteration":194,"passed_time":0.2892396714,"remaining_time":1.194040695},
{"learn":[0.196448286],"iteration":195,"passed_time":0.2907373059,"remaining_time":1.192616296},
{"learn":[0.1963076387],"iteration":196,"passed_time":0.2922050351,"remaining_time":1.191069255},
{"learn":[0.1954560259],"iteration":197,"passed_time":0.2938937979,"remaining_time":1.190418313},
{"learn":[0.1941087606],"iteration":198,"passed_time":0.2953636557,"remaining_time":1.18887582},
{"learn":[0.193544404],"iteration":199,"passed_time":0.296692287,"remaining_time":1.186769148},
{"learn":[0.193088824],"iteration":200,"passed_time":0.2980622229,"remaining_time":1.184834408},
{"learn":[0.1926956427],"iteration":201,"passed_time":0.2995251724,"remaining_time":1.183272711},
{"learn":[0.1920413492],"iteration":202,"passed_time":0.3009395423,"remaining_time":1.181521257},
{"learn":[0.1918945032],"iteration":203,"passed_time":0.3023259784,"remaining_time":1.179664112},
{"learn":[0.1916692826],"iteration":204,"passed_time":0.3036955996,"remaining_time":1.17774635},
{"learn":[0.1913265122],"iteration":205,"passed_time":0.3050222377,"remaining_time":1.175668236},
{"learn":[0.1904576441],"iteration":206,"passed_time":0.306401645,"remaining_time":1.173799539},
{"learn":[0.1897936462],"iteration":207,"passed_time":0.3077900446,"remaining_time":1.171969785},
{"learn":[0.1895178257],"iteration":208,"passed_time":0.3091819323,"remaining_time":1.170157457},
{"learn":[0.1890500225],"iteration":209,"passed_time":0.3105077616,"remaining_time":1.168100627},
{"learn":[0.1883495951],"iteration":210,"passed_time":0.3118278046,"remaining_time":1.166029089},
{"learn":[0.1880960948],"iteration":211,"passed_time":0.3139065403,"remaining_time":1.166784688},
{"learn":[0.1874812611],"iteration":212,"passed_time":0.315248137,"remaining_time":1.164790065},
{"learn":[0.1869957881],"iteration":213,"passed_time":0.3165664598,"remaining_time":1.162716063},
{"learn":[0.1868186838],"iteration":214,"passed_time":0.3178926411,"remaining_time":1.160677782},
{"learn":[0.1864875505],"iteration":215,"passed_time":0.3193019664,"remaining_time":1.158947878},
{"learn":[0.1861492696],"iteration":216,"passed_time":0.3213202069,"remaining_time":1.159418074},
{"learn":[0.1854777041],"iteration":217,"passed_time":0.3229277831,"remaining_time":1.158392323},
{"learn":[0.1850904263],"iteration":218,"passed_time":0.3246979528,"remaining_time":1.157941101},
{"learn":[0.184728099],"iteration":219,"passed_time":0.326252265,"remaining_time":1.156712576},
{"learn":[0.1842689324],"iteration":220,"passed_time":0.3277753846,"remaining_time":1.155371152},
{"learn":[0.1829744753],"iteration":221,"passed_time":0.3291716121,"remaining_time":1.153583397},
{"learn":[0.1825959428],"iteration":222,"passed_time":0.3306661694,"remaining_time":1.152141765},
{"learn":[0.1820483663],"iteration":223,"passed_time":0.3320933684,"remaining_time":1.150466312},
{"learn":[0.1813640024],"iteration":224,"passed_time":0.3334914538,"remaining_time":1.148692785},
{"learn":[0.1810500908],"iteration":225,"passed_time":0.3348712406,"remaining_time":1.146859912},
{"learn":[0.1806673642],"iteration":226,"passed_time":0.3365698476,"remaining_time":1.146116706},
{"learn":[0.180465907],"iteration":227,"passed_time":0.3379854221,"remaining_time":1.14440678},
{"learn":[0.1799345243],"iteration":228,"passed_time":0.3393678747,"remaining_time":1.14258791},
{"learn":[0.1796689679],"iteration":229,"passed_time":0.3407945835,"remaining_time":1.140920997},
{"learn":[0.1786756971],"iteration":230,"passed_time":0.3421063053,"remaining_time":1.138873371},
{"learn":[0.1774119905],"iteration":231,"passed_time":0.3434809665,"remaining_time":1.137040441},
{"learn":[0.1769181072],"iteration":232,"passed_time":0.3448237038,"remaining_time":1.135106355},
{"learn":[0.1765604352],"iteration":233,"passed_time":0.3461843788,"remaining_time":1.133236043},
{"learn":[0.1759169549],"iteration":234,"passed_time":0.3475326576,"remaining_time":1.131329715},
{"learn":[0.1754528459],"iteration":235,"passed_time":0.348924639,"remaining_time":1.129569594},
{"learn":[0.1751247911],"iteration":236,"passed_time":0.3503054443,"remaining_time":1.127776599},
{"learn":[0.1745774268],"iteration":237,"passed_time":0.3517158783,"remaining_time":1.12608193},
{"learn":[0.1739410149],"iteration":238,"passed_time":0.3530784751,"remaining_time":1.12423732},
{"learn":[0.1735670903],"iteration":239,"passed_time":0.3544428755,"remaining_time":1.122402439},
{"learn":[0.1733915466],"iteration":240,"passed_time":0.3557684578,"remaining_time":1.120449209},
{"learn":[0.1730475377],"iteration":241,"passed_time":0.3572731836,"remaining_time":1.119062286},
{"learn":[0.1725247554],"iteration":242,"passed_time":0.3586621174,"remaining_time":1.117313674},
{"learn":[0.1722339512],"iteration":243,"passed_time":0.3600671765,"remaining_time":1.115617973},
{"learn":[0.1717585023],"iteration":244,"passed_time":0.361425644,"remaining_time":1.113781066},
{"learn":[0.1710726798],"iteration":245,"passed_time":0.3628568274,"remaining_time":1.112170926},
{"learn":[0.1706886514],"iteration":246,"passed_time":0.3641746696,"remaining_time":1.110216705},
{"learn":[0.1703149959],"iteration":247,"passed_time":0.3655412276,"remaining_time":1.108415335},
{"learn":[0.1700550359],"iteration":248,"passed_time":0.3668734391,"remaining_time":1.106513867},
{"learn":[0.1694853928],"iteration":249,"passed_time":0.3682023703,"remaining_time":1.104607111},
{"learn":[0.1692934497],"iteration":250,"passed_time":0.3694968478,"remaining_time":1.102602148},
{"learn":[0.1688260092],"iteration":251,"passed_time":0.3709261071,"remaining_time":1.101002889},
{"learn":[0.1685276484],"iteration":252,"passed_time":0.3722630931,"remaining_time":1.099132532},
{"learn":[0.168396191],"iteration":253,"passed_time":0.3735387617,"remaining_time":1.097086284},
{"learn":[0.1681430529],"iteration":254,"passed_time":0.3749970276,"remaining_time":1.095579551},
{"learn":[0.1676481762],"iteration":255,"passed_time":0.3763521321,"remaining_time":1.093773384},
{"learn":[0.1672105531],"iteration":256,"passed_time":0.3776983164,"remaining_time":1.091944938},
{"learn":[0.1668698825],"iteration":257,"passed_time":0.3790440246,"remaining_time":1.090118861},
{"learn":[0.1666413886],"iteration":258,"passed_time":0.3803631234,"remaining_time":1.088220365},
{"learn":[0.1659777986],"iteration":259,"passed_time":0.3817041971,"remaining_time":1.086388869},
{"learn":[0.1652132169],"iteration":260,"passed_time":0.3830193794,"remaining_time":1.084487821},
{"learn":[0.1647732859],"iteration":261,"passed_time":0.3843369947,"remaining_time":1.082598099},
{"learn":[0.1645693637],"iteration":262,"passed_time":0.3856641193,"remaining_time":1.080739376},
{"learn":[0.1639473427],"iteration":263,"passed_time":0.3875957061,"remaining_time":1.080569847},
{"learn":[0.1636531472],"iteration":264,"passed_time":0.3891763583,"remaining_time":1.079413673},
{"learn":[0.1629598501],"iteration":265,"passed_time":0.3906038014,"remaining_time":1.077831542},
{"learn":[0.1625441389],"iteration":266,"passed_time":0.3919544774,"remaining_time":1.07603982},
{"learn":[0.1624522785],"iteration":267,"passed_time":0.3936480333,"remaining_time":1.075187912},
{"learn":[0.1622436624],"iteration":268,"passed_time":0.3956888561,"remaining_time":1.075273434},
{"learn":[0.1618224914],"iteration":269,"passed_time":0.3979367758,"remaining_time":1.075903135},
{"learn":[0.1615354184],"iteration":270,"passed_time":0.399857954,"remaining_time":1.075632651},
{"learn":[0.1609970339],"iteration":271,"passed_time":0.4013038646,"remaining_time":1.074077991},
{"learn":[0.1608645808],"iteration":272,"passed_time":0.402737818,"remaining_time":1.072492285},
{"learn":[0.1604784651],"iteration":273,"passed_time":0.4042067301,"remaining_time":1.071000314},
{"learn":[0.1599517783],"iteration":274,"passed_time":0.4058214453,"remaining_time":1.069892901},
{"learn":[0.1589377572],"iteration":275,"passed_time":0.4073458498,"remaining_time":1.06854491},
{"learn":[0.1583684665],"iteration":276,"passed_time":0.4087937567,"remaining_time":1.066995979},
{"learn":[0.157607997],"iteration":277,"passed_time":0.4101856242,"remaining_time":1.065302233},
{"learn":[0.1574198719],"iteration":278,"passed_time":0.4122003845,"remaining_time":1.065220348},
{"learn":[0.1566464308],"iteration":279,"passed_time":0.4156426214,"remaining_time":1.068795312},
{"learn":[0.1560550432],"iteration":280,"passed_time":0.4170758687,"remaining_time":1.067179892},
{"learn":[0.1550468196],"iteration":281,"passed_time":0.4185325163,"remaining_time":1.065625343},
{"learn":[0.1546165818],"iteration":282,"passed_time":0.4199075324,"remaining_time":1.063864667},
{"learn":[0.1542287718],"iteration":283,"passed_time":0.4212733196,"remaining_time":1.06208344},
{"learn":[0.1539566026],"iteration":284,"passed_time":0.422647149,"remaining_time":1.060325304},
{"learn":[0.1536969945],"iteration":285,"passed_time":0.4240625136,"remaining_time":1.058673548},
{"learn":[0.1532674919],"iteration":286,"passed_time":0.4254648898,"remaining_time":1.056991172},
{"learn":[0.1529232606],"iteration":287,"passed_time":0.4269704132,"remaining_time":1.055565744},
{"learn":[0.151968757],"iteration":288,"passed_time":0.4290361731,"remaining_time":1.055518059},
{"learn":[0.1518990531],"iteration":289,"passed_time":0.4304078367,"remaining_time":1.053757117},
{"learn":[0.1513719176],"iteration":290,"passed_time":0.4317697021,"remaining_time":1.051974979},
{"learn":[0.1510193091],"iteration":291,"passed_time":0.4330889765,"remaining_time":1.05009245},
{"learn":[0.1505183848],"iteration":292,"passed_time":0.4344309185,"remaining_time":1.048268462},
{"learn":[0.1502947649],"iteration":293,"passed_time":0.4357345676,"remaining_time":1.046355798},
{"learn":[0.1500796137],"iteration":294,"passed_time":0.4370611759,"remaining_time":1.044502132},
{"learn":[0.1496272869],"iteration":295,"passed_time":0.4384698644,"remaining_time":1.042847245},
{"learn":[0.149309258],"iteration":296,"passed_time":0.4398322172,"remaining_time":1.041084339},
{"learn":[0.1490238312],"iteration":297,"passed_time":0.4411422077,"remaining_time":1.039200771},
{"learn":[0.1486649965],"iteration":298,"passed_time":0.4425119256,"remaining_time":1.03746107},
{"learn":[0.1483284505],"iteration":299,"passed_time":0.4438443655,"remaining_time":1.035636853},
{"learn":[0.1479558909],"iteration":300,"passed_time":0.4452614786,"remaining_time":1.034012537},
{"learn":[0.1475143392],"iteration":301,"passed_time":0.4470413779,"remaining_time":1.033228085},
{"learn":[0.1472854865],"iteration":302,"passed_time":0.4486671723,"remaining_time":1.032082571},
{"learn":[0.1470200421],"iteration":303,"passed_time":0.4502556874,"remaining_time":1.030848547},
{"learn":[0.1466529456],"iteration":304,"passed_time":0.4516361244,"remaining_time":1.029138054},
{"learn":[0.1459018171],"iteration":305,"passed_time":0.4530590551,"remaining_time":1.027526092},
{"learn":[0.1456492181],"iteration":306,"passed_time":0.4544544746,"remaining_time":1.02585326},
{"learn":[0.1453796329],"iteration":307,"passed_time":0.4558524431,"remaining_time":1.024187957},
{"learn":[0.1451318094],"iteration":308,"passed_time":0.4572038133,"remaining_time":1.022420178},
{"learn":[0.1448576421],"iteration":309,"passed_time":0.458610548,"remaining_time":1.020778317},
{"learn":[0.1446213936],"iteration":310,"passed_time":0.459968645,"remaining_time":1.019030213},
{"learn":[0.1442288897],"iteration":311,"passed_time":0.4613735463,"remaining_time":1.01738782},
{"learn":[0.1436970865],"iteration":312,"passed_time":0.4627149444,"remaining_time":1.015607562},
{"learn":[0.1434692275],"iteration":313,"passed_time":0.4640196947,"remaining_time":1.013750034},
{"learn":[0.1432191505],"iteration":314,"passed_time":0.4653333934,"remaining_time":1.011915475},
{"learn":[0.1429680728],"iteration":315,"passed_time":0.4666718265,"remaining_time":1.010137751},
{"learn":[0.1428150321],"iteration":316,"passed_time":0.4680146702,"remaining_time":1.008372302},
{"learn":[0.142578205],"iteration":317,"passed_time":0.469420512,"remaining_time":1.00674462},
{"learn":[0.1419732562],"iteration":318,"passed_time":0.4708453883,"remaining_time":1.005158964},
{"learn":[0.1417150652],"iteration":319,"passed_time":0.4721855177,"remaining_time":1.003394225},
{"learn":[0.141569018],"iteration":320,"passed_time":0.4735477865,"remaining_time":1.001678963},
{"learn":[0.1412152234],"iteration":321,"passed_time":0.4748628638,"remaining_time":0.999866527},
{"learn":[0.1409604196],"iteration":322,"passed_time":0.4761857148,"remaining_time":0.9980734642},
{"learn":[0.1407061421],"iteration":323,"passed_time":0.4776234121,"remaining_time":0.9965229216},
{"learn":[0.1404565135],"iteration":324,"passed_time":0.4789733672,"remaining_time":0.9947908395},
{"learn":[0.1403229974],"iteration":325,"passed_time":0.4803001176,"remaining_time":0.9930131266},
{"learn":[0.1399468991],"iteration":326,"passed_time":0.4817021329,"remaining_time":0.9913930748},
{"learn":[0.1396060584],"iteration":327,"passed_time":0.483107695,"remaining_time":0.989781619},
{"learn":[0.1394121557],"iteration":328,"passed_time":0.4845275029,"remaining_time":0.9882004695},
{"learn":[0.139256144],"iteration":329,"passed_time":0.4859348611,"remaining_time":0.986595021},
{"learn":[0.1389802316],"iteration":330,"passed_time":0.4873103184,"remaining_time":0.9849262931},
{"learn":[0.1387268243],"iteration":331,"passed_time":0.4887286561,"remaining_time":0.9833456093},
{"learn":[0.1385411543],"iteration":332,"passed_time":0.4901499045,"remaining_time":0.9817717306},
{"learn":[0.1378607967],"iteration":333,"passed_time":0.4914987748,"remaining_time":0.9800544432},
{"learn":[0.1375929529],"iteration":334,"passed_time":0.4928985089,"remaining_time":0.9784403237},
{"learn":[0.1373576131],"iteration":335,"passed_time":0.4943064735,"remaining_time":0.9768437452},
{"learn":[0.1368379213],"iteration":336,"passed_time":0.4956574746,"remaining_time":0.9751362187},
{"learn":[0.136365859],"iteration":337,"passed_time":0.4969814446,"remaining_time":0.973377859},
{"learn":[0.1359243748],"iteration":338,"passed_time":0.4983757362,"remaining_time":0.9717591789},
{"learn":[0.135415859],"iteration":339,"passed_time":0.4997152325,"remaining_time":0.9700354514},
{"learn":[0.1352185797],"iteration":340,"passed_time":0.5010221115,"remaining_time":0.9682509427},
{"learn":[0.135052216],"iteration":341,"passed_time":0.5023447459,"remaining_time":0.9664995404},
{"learn":[0.1348582021],"iteration":342,"passed_time":0.5036273637,"remaining_time":0.9646739882},
{"learn":[0.1347281358],"iteration":343,"passed_time":0.5049820687,"remaining_time":0.9629890612},
{"learn":[0.1345742872],"iteration":344,"passed_time":0.5063209973,"remaining_time":0.9612760963},
{"learn":[0.1343738049],"iteration":345,"passed_time":0.5076862295,"remaining_time":0.9596150117},
{"learn":[0.1342461887],"iteration":346,"passed_time":0.5090278262,"remaining_time":0.9579111541},
{"learn":[0.1340564847],"iteration":347,"passed_time":0.5103257686,"remaining_time":0.9561275895},
{"learn":[0.1337491187],"iteration":348,"passed_time":0.5116837145,"remaining_time":0.954458734},
{"learn":[0.1334012562],"iteration":349,"passed_time":0.5131180585,"remaining_time":0.9529335372},
{"learn":[0.1329038224],"iteration":350,"passed_time":0.5145012358,"remaining_time":0.9513142509},
{"learn":[0.1323775232],"iteration":351,"passed_time":0.5165785668,"remaining_time":0.9509741799},
{"learn":[0.1320256251],"iteration":352,"passed_time":0.5181114503,"remaining_time":0.9496263693},
{"learn":[0.131886516],"iteration":353,"passed_time":0.519507686,"remaining_time":0.9480281502},
{"learn":[0.1316714597],"iteration":354,"passed_time":0.5210019241,"remaining_time":0.9466091297},
{"learn":[0.1312363476],"iteration":355,"passed_time":0.522416817,"remaining_time":0.9450461521},
{"learn":[0.1310870744],"iteration":356,"passed_time":0.5237479289,"remaining_time":0.9433331044},
{"learn":[0.1308321803],"iteration":357,"passed_time":0.5251233973,"remaining_time":0.9417017349},
{"learn":[0.1306702959],"iteration":358,"passed_time":0.5265533836,"remaining_time":0.9401691333},
{"learn":[0.1302518289],"iteration":359,"passed_time":0.5279031943,"remaining_time":0.9384945676},
{"learn":[0.1300176135],"iteration":360,"passed_time":0.5292569528,"remaining_time":0.9368287891},
{"learn":[0.129897255],"iteration":361,"passed_time":0.5306489268,"remaining_time":0.9352320864},
{"learn":[0.1297761384],"iteration":362,"passed_time":0.5319765998,"remaining_time":0.9335236751},
{"learn":[0.1293812445],"iteration":363,"passed_time":0.5333140545,"remaining_time":0.9318344468},
{"learn":[0.1291910261],"iteration":364,"passed_time":0.5354555019,"remaining_time":0.9315458732},
{"learn":[0.1284779852],"iteration":365,"passed_time":0.5370528991,"remaining_time":0.9303047487},
{"learn":[0.1282016706],"iteration":366,"passed_time":0.5384535573,"remaining_time":0.9287223482},
{"learn":[0.1280032018],"iteration":367,"passed_time":0.5398089475,"remaining_time":0.9270631925},
{"learn":[0.1277553435],"iteration":368,"passed_time":0.5412098431,"remaining_time":0.9254834986},
{"learn":[0.127445368],"iteration":369,"passed_time":0.542542135,"remaining_time":0.9237879596},
{"learn":[0.1270888931],"iteration":370,"passed_time":0.5439453928,"remaining_time":0.9222146956},
{"learn":[0.1267441691],"iteration":371,"passed_time":0.5453018179,"remaining_time":0.920563284},
{"learn":[0.1262944537],"iteration":372,"passed_time":0.5466297432,"remaining_time":0.9188655468},
{"learn":[0.1261678722],"iteration":373,"passed_time":0.5479571081,"remaining_time":0.9171688494},
{"learn":[0.1259924177],"iteration":374,"passed_time":0.54927605,"remaining_time":0.9154600833},
{"learn":[0.1257772837],"iteration":375,"passed_time":0.550678133,"remaining_time":0.9138913697},
{"learn":[0.1256488422],"iteration":376,"passed_time":0.5520347724,"remaining_time":0.9122484435},
{"learn":[0.1252899985],"iteration":377,"passed_time":0.5534984801,"remaining_time":0.9107832133},
{"learn":[0.1249880385],"iteration":378,"passed_time":0.5549228623,"remaining_time":0.9092535554},
{"learn":[0.1247939713],"iteration":379,"passed_time":0.5562884464,"remaining_time":0.9076285178},
{"learn":[0.124422227],"iteration":380,"passed_time":0.5576838496,"remaining_time":0.9060532884},
{"learn":[0.1242301228],"iteration":381,"passed_time":0.5590334349,"remaining_time":0.9044048763},
{"learn":[0.1240901334],"iteration":382,"passed_time":0.5604020821,"remaining_time":0.9027887328},
{"learn":[0.1237427336],"iteration":383,"passed_time":0.5617373776,"remaining_time":0.9011203766},
{"learn":[0.123611896],"iteration":384,"passed_time":0.5630859912,"remaining_time":0.899475025},
{"learn":[0.1234658846],"iteration":385,"passed_time":0.564446792,"remaining_time":0.8978505966},
{"learn":[0.1230699593],"iteration":386,"passed_time":0.5657618597,"remaining_time":0.8961550904},
{"learn":[0.1220866315],"iteration":387,"passed_time":0.5671462208,"remaining_time":0.8945708431},
{"learn":[0.1219271425],"iteration":388,"passed_time":0.5684832819,"remaining_time":0.8929133297},
{"learn":[0.1207671912],"iteration":389,"passed_time":0.5698591975,"remaining_time":0.891318232},
{"learn":[0.1205928468],"iteration":390,"passed_time":0.571272708,"remaining_time":0.8897828112},
{"learn":[0.1201436874],"iteration":391,"passed_time":0.5726577365,"remaining_time":0.8882038362},
{"learn":[0.1200747507],"iteration":392,"passed_time":0.5739207388,"remaining_time":0.8864373751},
{"learn":[0.1198404051],"iteration":393,"passed_time":0.57545169,"remaining_time":0.8850855943},
{"learn":[0.1192187019],"iteration":394,"passed_time":0.5769154505,"remaining_time":0.8836299938},
{"learn":[0.1190392971],"iteration":395,"passed_time":0.5782957299,"remaining_time":0.8820470223},
{"learn":[0.1189471822],"iteration":396,"passed_time":0.5797654151,"remaining_time":0.8806008697},
{"learn":[0.1186219611],"iteration":397,"passed_time":0.5813902103,"remaining_time":0.8793892125},
{"learn":[0.1183558657],"iteration":398,"passed_time":0.582789963,"remaining_time":0.8778365107},
{"learn":[0.1181101338],"iteration":399,"passed_time":0.5841761172,"remaining_time":0.8762641757},
{"learn":[0.117518039],"iteration":400,"passed_time":0.5855484139,"remaining_time":0.8746720696},
{"learn":[0.1172668325],"iteration":401,"passed_time":0.5869326559,"remaining_time":0.8730988264},
{"learn":[0.1168597817],"iteration":402,"passed_time":0.5882898846,"remaining_time":0.8714865039},
{"learn":[0.1166986011],"iteration":403,"passed_time":0.5896330095,"remaining_time":0.8698546377},
{"learn":[0.1164544736],"iteration":404,"passed_time":0.5913036054,"remaining_time":0.8687052969},
{"learn":[0.1162028038],"iteration":405,"passed_time":0.5927840366,"remaining_time":0.8672751668},
{"learn":[0.1160284046],"iteration":406,"passed_time":0.5941153568,"remaining_time":0.8656275346},
{"learn":[0.1159529932],"iteration":407,"passed_time":0.5954499321,"remaining_time":0.863986176},
{"learn":[0.1155654458],"iteration":408,"passed_time":0.5971138028,"remaining_time":0.8628221454},
{"learn":[0.114863991],"iteration":409,"passed_time":0.5984614172,"remaining_time":0.861200576},
{"learn":[0.114696992],"iteration":410,"passed_time":0.5998324907,"remaining_time":0.8596139587},
{"learn":[0.1144596901],"iteration":411,"passed_time":0.6011447386,"remaining_time":0.8579444327},
{"learn":[0.1142307283],"iteration":412,"passed_time":0.6024422577,"remaining_time":0.8562557028},
{"learn":[0.1138766192],"iteration":413,"passed_time":0.6038942291,"remaining_time":0.8547874837},
{"learn":[0.1136626388],"iteration":414,"passed_time":0.605414459,"remaining_time":0.8534155626},
{"learn":[0.1134982227],"iteration":415,"passed_time":0.6067679162,"remaining_time":0.8518088054},
{"learn":[0.113289602],"iteration":416,"passed_time":0.608109806,"remaining_time":0.8501870909},
{"learn":[0.1129844851],"iteration":417,"passed_time":0.6096515516,"remaining_time":0.8488449833},
{"learn":[0.1128359874],"iteration":418,"passed_time":0.6109879349,"remaining_time":0.8472171603},
{"learn":[0.1125982489],"iteration":419,"passed_time":0.6123395365,"remaining_time":0.8456117409},
{"learn":[0.112429431],"iteration":420,"passed_time":0.6138067329,"remaining_time":0.8441665044},
{"learn":[0.1121953005],"iteration":421,"passed_time":0.6152784992,"remaining_time":0.842727423},
{"learn":[0.1115334181],"iteration":422,"passed_time":0.616864303,"remaining_time":0.8414437419},
{"learn":[0.1113546349],"iteration":423,"passed_time":0.6183152566,"remaining_time":0.8399754429},
{"learn":[0.1109844011],"iteration":424,"passed_time":0.6196950374,"remaining_time":0.838410933},
{"learn":[0.1109205973],"iteration":425,"passed_time":0.6211550242,"remaining_time":0.8369553613},
{"learn":[0.1107303493],"iteration":426,"passed_time":0.6232233912,"remaining_time":0.8363161667},
{"learn":[0.110593419],"iteration":427,"passed_time":0.624800231,"remaining_time":0.8350133928},
{"learn":[0.1103479091],"iteration":428,"passed_time":0.626160505,"remaining_time":0.8334210917},
{"learn":[0.1100642243],"iteration":429,"passed_time":0.6275622301,"remaining_time":0.8318848167},
{"learn":[0.1098222731],"iteration":430,"passed_time":0.6289108578,"remaining_time":0.8302790676},
{"learn":[0.1096066248],"iteration":431,"passed_time":0.6302665643,"remaining_time":0.828683816},
{"learn":[0.1093418822],"iteration":432,"passed_time":0.6316470162,"remaining_time":0.8271220743},
{"learn":[0.1092048844],"iteration":433,"passed_time":0.6330181277,"remaining_time":0.8255489868},
{"learn":[0.1090689114],"iteration":434,"passed_time":0.6343807334,"remaining_time":0.8239657802},
{"learn":[0.1089167688],"iteration":435,"passed_time":0.6357016276,"remaining_time":0.8223296284},
{"learn":[0.1088199305],"iteration":436,"passed_time":0.6370453671,"remaining_time":0.8207243516},
{"learn":[0.108736314],"iteration":437,"passed_time":0.6384128068,"remaining_time":0.819150679},
{"learn":[0.108641389],"iteration":438,"passed_time":0.6397698435,"remaining_time":0.8175646519},
{"learn":[0.1082908628],"iteration":439,"passed_time":0.6412394617,"remaining_time":0.8161229513},
{"learn":[0.108142562],"iteration":440,"passed_time":0.6425535585,"remaining_time":0.8144839891},
{"learn":[0.10793999],"iteration":441,"passed_time":0.6443135409,"remaining_time":0.8134094024},
{"learn":[0.1077839839],"iteration":442,"passed_time":0.6461333141,"remaining_time":0.8124068983},
{"learn":[0.1076431165],"iteration":443,"passed_time":0.6479802835,"remaining_time":0.8114347695},
{"learn":[0.107339874],"iteration":444,"passed_time":0.6493816456,"remaining_time":0.8099029512},
{"learn":[0.10715424],"iteration":445,"passed_time":0.6507955966,"remaining_time":0.8083873554},
{"learn":[0.1069476482],"iteration":446,"passed_time":0.6521953277,"remaining_time":0.8068546224},
{"learn":[0.1065685469],"iteration":447,"passed_time":0.6537288235,"remaining_time":0.8054873004},
{"learn":[0.1064249863],"iteration":448,"passed_time":0.6554069557,"remaining_time":0.8042967318},
{"learn":[0.1058528165],"iteration":449,"passed_time":0.6568428026,"remaining_time":0.8028078699},
{"learn":[0.1056027772],"iteration":450,"passed_time":0.6581817439,"remaining_time":0.8012012802},
{"learn":[0.1054515044],"iteration":451,"passed_time":0.6595763152,"remaining_time":0.7996633202},
{"learn":[0.1053450524],"iteration":452,"passed_time":0.6609187861,"remaining_time":0.7980630817},
{"learn":[0.1051945473],"iteration":453,"passed_time":0.6622115085,"remaining_time":0.796404149},
{"learn":[0.1048675331],"iteration":454,"passed_time":0.6635543626,"remaining_time":0.7948068739},
{"learn":[0.1047311103],"iteration":455,"passed_time":0.664971222,"remaining_time":0.7932990017},
{"learn":[0.1046524418],"iteration":456,"passed_time":0.6662895128,"remaining_time":0.7916744102},
{"learn":[0.1043683102],"iteration":457,"passed_time":0.6676894047,"remaining_time":0.7901477234},
{"learn":[0.1041354002],"iteration":458,"passed_time":0.6691056539,"remaining_time":0.7886408688},
{"learn":[0.1036697015],"iteration":459,"passed_time":0.6705046887,"remaining_time":0.7871141998},
{"learn":[0.1035286013],"iteration":460,"passed_time":0.6718431091,"remaining_time":0.7855172144},
{"learn":[0.1033303665],"iteration":461,"passed_time":0.6732534129,"remaining_time":0.7840050566},
{"learn":[0.1032422972],"iteration":462,"passed_time":0.674637332,"remaining_time":0.7824627371},
{"learn":[0.1030730581],"iteration":463,"passed_time":0.6759742041,"remaining_time":0.7808667531},
{"learn":[0.1030187106],"iteration":464,"passed_time":0.6773178938,"remaining_time":0.7792797273},
{"learn":[0.1028094424],"iteration":465,"passed_time":0.6788573269,"remaining_time":0.7779180527},
{"learn":[0.1027539411],"iteration":466,"passed_time":0.6805046907,"remaining_time":0.7766788011},
{"learn":[0.1025113119],"iteration":467,"passed_time":0.6818608316,"remaining_time":0.7751067573},
{"learn":[0.1025071981],"iteration":468,"passed_time":0.6826371718,"remaining_time":0.772879186},
{"learn":[0.1022831368],"iteration":469,"passed_time":0.6842964274,"remaining_time":0.7716534181},
{"learn":[0.1021944027],"iteration":470,"passed_time":0.6857221488,"remaining_time":0.7701635175},
{"learn":[0.1020259313],"iteration":471,"passed_time":0.6870530561,"remaining_time":0.7685678255},
{"learn":[0.1018618193],"iteration":472,"passed_time":0.6885104931,"remaining_time":0.7671142281},
{"learn":[0.1016477502],"iteration":473,"passed_time":0.6898697612,"remaining_time":0.7655516759},
{"learn":[0.1014801544],"iteration":474,"passed_time":0.6912196553,"remaining_time":0.763979619},
{"learn":[0.1010885247],"iteration":475,"passed_time":0.6926117162,"remaining_time":0.7624549145},
{"learn":[0.1008948556],"iteration":476,"passed_time":0.6938997513,"remaining_time":0.7608167084},
{"learn":[0.1006180214],"iteration":477,"passed_time":0.6952427929,"remaining_time":0.7592400374},
{"learn":[0.1004457572],"iteration":478,"passed_time":0.6965615219,"remaining_time":0.7576378976},
{"learn":[0.09994227183],"iteration":479,"passed_time":0.6979684262,"remaining_time":0.7561324618},
{"learn":[0.09981181369],"iteration":480,"passed_time":0.6992916901,"remaining_time":0.7545371875},
{"learn":[0.09960893165],"iteration":481,"passed_time":0.7006378358,"remaining_time":0.7529676327},
{"learn":[0.0994986846],"iteration":482,"passed_time":0.7020105811,"remaining_time":0.7514274751},
{"learn":[0.09930482667],"iteration":483,"passed_time":0.7033858145,"remaining_time":0.7498906617},
{"learn":[0.09911071342],"iteration":484,"passed_time":0.704715323,"remaining_time":0.7483059616},
{"learn":[0.09893601038],"iteration":485,"passed_time":0.7061350945,"remaining_time":0.7468177748},
{"learn":[0.09880106963],"iteration":486,"passed_time":0.707452436,"remaining_time":0.7452219705},
{"learn":[0.09872093577],"iteration":487,"passed_time":0.7088194553,"remaining_time":0.7436794285},
{"learn":[0.09865148647],"iteration":488,"passed_time":0.7102109687,"remaining_time":0.7421632004},
{"learn":[0.09852825953],"iteration":489,"passed_time":0.7116882957,"remaining_time":0.7407367976},
{"learn":[0.09827334826],"iteration":490,"passed_time":0.7134783093,"remaining_time":0.7396343369},
{"learn":[0.09804442695],"iteration":491,"passed_time":0.7148574793,"remaining_time":0.738104877},
{"learn":[0.09787826006],"iteration":492,"passed_time":0.7162106731,"remaining_time":0.7365493129},
{"learn":[0.09764145121],"iteration":493,"passed_time":0.7177383774,"remaining_time":0.7351733178},
{"learn":[0.09751897904],"iteration":494,"passed_time":0.7191680601,"remaining_time":0.7336967078},
{"learn":[0.09736271321],"iteration":495,"passed_time":0.7205687198,"remaining_time":0.7321907959},
{"learn":[0.09718244948],"iteration":496,"passed_time":0.7219734776,"remaining_time":0.7306894552},
{"learn":[0.09678092875],"iteration":497,"passed_time":0.7233714774,"remaining_time":0.72918169},
{"learn":[0.09660133026],"iteration":498,"passed_time":0.7247495358,"remaining_time":0.7276543436},
{"learn":[0.0964966675],"iteration":499,"passed_time":0.7260992223,"remaining_time":0.7260992223},
{"learn":[0.0962107414],"iteration":500,"passed_time":0.7275012941,"remaining_time":0.7245970974},
{"learn":[0.09612184774],"iteration":501,"passed_time":0.7288580221,"remaining_time":0.7230503884},
{"learn":[0.09594870449],"iteration":502,"passed_time":0.7301990139,"remaining_time":0.7214888865},
{"learn":[0.09587154967],"iteration":503,"passed_time":0.7315064836,"remaining_time":0.7198952696},
{"learn":[0.09573147629],"iteration":504,"passed_time":0.732912632,"remaining_time":0.7183995106},
{"learn":[0.09544219318],"iteration":505,"passed_time":0.7343318209,"remaining_time":0.716916837},
{"learn":[0.09523913343],"iteration":506,"passed_time":0.7356818578,"remaining_time":0.7153671714},
{"learn":[0.09505272587],"iteration":507,"passed_time":0.7369975758,"remaining_time":0.7137850537},
{"learn":[0.0949591423],"iteration":508,"passed_time":0.738315889,"remaining_time":0.7122064862},
{"learn":[0.09464332356],"iteration":509,"passed_time":0.7396306241,"remaining_time":0.7106255016},
{"learn":[0.09438795062],"iteration":510,"passed_time":0.7410210222,"remaining_time":0.7091179645},
{"learn":[0.09427501627],"iteration":511,"passed_time":0.7424263908,"remaining_time":0.7076251538},
{"learn":[0.09418184781],"iteration":512,"passed_time":0.7448079651,"remaining_time":0.7070594133},
{"learn":[0.09400760083],"iteration":513,"passed_time":0.7466961953,"remaining_time":0.706020138},
{"learn":[0.09382947127],"iteration":514,"passed_time":0.7481148656,"remaining_time":0.7045353589},
{"learn":[0.09370874772],"iteration":515,"passed_time":0.7496241322,"remaining_time":0.703135814},
{"learn":[0.09359884367],"iteration":516,"passed_time":0.7510983061,"remaining_time":0.7017030597},
{"learn":[0.09345544912],"iteration":517,"passed_time":0.7527082566,"remaining_time":0.7003964858},
{"learn":[0.09338608278],"iteration":518,"passed_time":0.7541669473,"remaining_time":0.6989485581},
{"learn":[0.09328159073],"iteration":519,"passed_time":0.7555573513,"remaining_time":0.6974375551},
{"learn":[0.09306686645],"iteration":520,"passed_time":0.7569881262,"remaining_time":0.6959641314},
{"learn":[0.09287581164],"iteration":521,"passed_time":0.7583928408,"remaining_time":0.6944670075},
{"learn":[0.09275976384],"iteration":522,"passed_time":0.7597619412,"remaining_time":0.6929377552},
{"learn":[0.09266739241],"iteration":523,"passed_time":0.7610829604,"remaining_time":0.6913654373},
{"learn":[0.09260792128],"iteration":524,"passed_time":0.7624307593,"remaining_time":0.689818306},
{"learn":[0.09243689616],"iteration":525,"passed_time":0.7637771274,"remaining_time":0.6882706433},
{"learn":[0.09237784757],"iteration":526,"passed_time":0.7660484363,"remaining_time":0.6875539096},
{"learn":[0.09222406083],"iteration":527,"passed_time":0.7673878724,"remaining_time":0.6859982495},
{"learn":[0.09213501124],"iteration":528,"passed_time":0.7687243822,"remaining_time":0.6844408015},
{"learn":[0.09186358929],"iteration":529,"passed_time":0.7701339211,"remaining_time":0.6829489489},
{"learn":[0.0917777616],"iteration":530,"passed_time":0.7714973155,"remaining_time":0.6814166496},
{"learn":[0.09167444072],"iteration":531,"passed_time":0.772873955,"remaining_time":0.6798966371},
{"learn":[0.09139632089],"iteration":532,"passed_time":0.7742167169,"remaining_time":0.6783474799},
{"learn":[0.09134206176],"iteration":533,"passed_time":0.7756165314,"remaining_time":0.6768488832},
{"learn":[0.09109835053],"iteration":534,"passed_time":0.7771323223,"remaining_time":0.6754514577},
{"learn":[0.09086505772],"iteration":535,"passed_time":0.7785832053,"remaining_time":0.6739974016},
{"learn":[0.09081105856],"iteration":536,"passed_time":0.7799051939,"remaining_time":0.6724322249},
{"learn":[0.09072663581],"iteration":537,"passed_time":0.7812470094,"remaining_time":0.6708849783},
{"learn":[0.09063751594],"iteration":538,"passed_time":0.7825934125,"remaining_time":0.6693424177},
{"learn":[0.09057065028],"iteration":539,"passed_time":0.7840860122,"remaining_time":0.6679251215},
{"learn":[0.09042450528],"iteration":540,"passed_time":0.785474449,"remaining_time":0.6664191721},
{"learn":[0.09033634815],"iteration":541,"passed_time":0.78680654,"remaining_time":0.664866043},
{"learn":[0.09016001684],"iteration":542,"passed_time":0.7884069937,"remaining_time":0.6635395877},
{"learn":[0.08999388712],"iteration":543,"passed_time":0.7899384538,"remaining_time":0.6621542922},
{"learn":[0.08979561355],"iteration":544,"passed_time":0.7914280075,"remaining_time":0.6607334741},
{"learn":[0.08960077483],"iteration":545,"passed_time":0.7927906564,"remaining_time":0.6592068828},
{"learn":[0.08943550855],"iteration":546,"passed_time":0.7941296021,"remaining_time":0.657661261},
{"learn":[0.08928362563],"iteration":547,"passed_time":0.7955908025,"remaining_time":0.6562172312},
{"learn":[0.08918975416],"iteration":548,"passed_time":0.7969210513,"remaining_time":0.6546655631},
{"learn":[0.08902575608],"iteration":549,"passed_time":0.7982716254,"remaining_time":0.6531313299},
{"learn":[0.08898837771],"iteration":550,"passed_time":0.7995251629,"remaining_time":0.6515186899},
{"learn":[0.08886347808],"iteration":551,"passed_time":0.8014797215,"remaining_time":0.6504762957},
{"learn":[0.08874573011],"iteration":552,"passed_time":0.8028884457,"remaining_time":0.6489893946},
{"learn":[0.08847691432],"iteration":553,"passed_time":0.8042533921,"remaining_time":0.6474675323},
{"learn":[0.08842003094],"iteration":554,"passed_time":0.8055813285,"remaining_time":0.6459165607},
{"learn":[0.08832186234],"iteration":555,"passed_time":0.8069445622,"remaining_time":0.6443945785},
{"learn":[0.08824360517],"iteration":556,"passed_time":0.8082977025,"remaining_time":0.6428651386},
{"learn":[0.08800515547],"iteration":557,"passed_time":0.8097067727,"remaining_time":0.6413806335},
{"learn":[0.08786208215],"iteration":558,"passed_time":0.8110297784,"remaining_time":0.6398285014},
{"learn":[0.08770939186],"iteration":559,"passed_time":0.8123742336,"remaining_time":0.6382940407},
{"learn":[0.08761398983],"iteration":560,"passed_time":0.8139473622,"remaining_time":0.6369392014},
{"learn":[0.08742805807],"iteration":561,"passed_time":0.8152884411,"remaining_time":0.6354027352},
{"learn":[0.08724656901],"iteration":562,"passed_time":0.8168752456,"remaining_time":0.6340576951},
{"learn":[0.08702620758],"iteration":563,"passed_time":0.8183102041,"remaining_time":0.6325944131},
{"learn":[0.08693343728],"iteration":564,"passed_time":0.8196485338,"remaining_time":0.6310568358},
{"learn":[0.08687916298],"iteration":565,"passed_time":0.8209702107,"remaining_time":0.6295071934},
{"learn":[0.08666172175],"iteration":566,"passed_time":0.8224111683,"remaining_time":0.628049446},
{"learn":[0.08624256953],"iteration":567,"passed_time":0.8237737123,"remaining_time":0.6265321192},
{"learn":[0.08615986425],"iteration":568,"passed_time":0.8251472218,"remaining_time":0.6250236425},
{"learn":[0.0861179546],"iteration":569,"passed_time":0.8264766001,"remaining_time":0.6234823474},
{"learn":[0.08597975773],"iteration":570,"passed_time":0.8278598332,"remaining_time":0.6219822565},
{"learn":[0.08591393022],"iteration":571,"passed_time":0.8291918922,"remaining_time":0.620444283},
{"learn":[0.08575966876],"iteration":572,"passed_time":0.8306378913,"remaining_time":0.6189919365},
{"learn":[0.08565663951],"iteration":573,"passed_time":0.8320238915,"remaining_time":0.6174950832},
{"learn":[0.08545492299],"iteration":574,"passed_time":0.8333690134,"remaining_time":0.6159684012},
{"learn":[0.08535409256],"iteration":575,"passed_time":0.8347082128,"remaining_time":0.61443799},
{"learn":[0.08524304958],"iteration":576,"passed_time":0.8361590682,"remaining_time":0.6129900968},
{"learn":[0.08516449688],"iteration":577,"passed_time":0.8375284141,"remaining_time":0.611482683},
{"learn":[0.08504733117],"iteration":578,"passed_time":0.838860898,"remaining_time":0.6099489431},
{"learn":[0.08487862179],"iteration":579,"passed_time":0.8402627942,"remaining_time":0.6084661614},
{"learn":[0.08477361847],"iteration":580,"passed_time":0.8421161668,"remaining_time":0.6073092494},
{"learn":[0.08447885094],"iteration":581,"passed_time":0.8437714782,"remaining_time":0.606007694},
{"learn":[0.08420243332],"iteration":582,"passed_time":0.8452855818,"remaining_time":0.6046039238},
{"learn":[0.08409353111],"iteration":583,"passed_time":0.8467795572,"remaining_time":0.603185438},
{"learn":[0.08395596903],"iteration":584,"passed_time":0.8482248562,"remaining_time":0.6017321629},
{"learn":[0.08385978053],"iteration":585,"passed_time":0.8495994512,"remaining_time":0.6002289638},
{"learn":[0.08370696526],"iteration":586,"passed_time":0.8509459688,"remaining_time":0.5987064483},
{"learn":[0.08356444417],"iteration":587,"passed_time":0.8523406741,"remaining_time":0.5972182955},
{"learn":[0.08340345731],"iteration":588,"passed_time":0.8539740576,"remaining_time":0.5958970079},
{"learn":[0.08330927633],"iteration":589,"passed_time":0.8555351478,"remaining_time":0.5945244248},
{"learn":[0.08312658015],"iteration":590,"passed_time":0.8586159285,"remaining_time":0.5942029014},
{"learn":[0.08301869512],"iteration":591,"passed_time":0.8603483612,"remaining_time":0.5929427895},
{"learn":[0.0829933888],"iteration":592,"passed_time":0.8617822464,"remaining_time":0.5914761793},
{"learn":[0.08286808621],"iteration":593,"passed_time":0.8642554754,"remaining_time":0.5907200724},
{"learn":[0.08279813403],"iteration":594,"passed_time":0.8658445321,"remaining_time":0.5893563622},
{"learn":[0.08265361656],"iteration":595,"passed_time":0.8677302341,"remaining_time":0.5881929775},
{"learn":[0.08249433056],"iteration":596,"passed_time":0.8695011537,"remaining_time":0.58694969},
{"learn":[0.08239253131],"iteration":597,"passed_time":0.8712610692,"remaining_time":0.5856972405},
{"learn":[0.08235886305],"iteration":598,"passed_time":0.8729690755,"remaining_time":0.584408346},
{"learn":[0.0822503234],"iteration":599,"passed_time":0.8746687606,"remaining_time":0.5831125071},
{"learn":[0.08217418358],"iteration":600,"passed_time":0.8761997067,"remaining_time":0.5817032994},
{"learn":[0.08203650614],"iteration":601,"passed_time":0.8776044749,"remaining_time":0.5802102674},
{"learn":[0.0818712114],"iteration":602,"passed_time":0.8791754361,"remaining_time":0.5788269455},
{"learn":[0.08176859926],"iteration":603,"passed_time":0.8806398387,"remaining_time":0.5773731393},
{"learn":[0.08168158572],"iteration":604,"passed_time":0.881968787,"remaining_time":0.5758308609},
{"learn":[0.08155725425],"iteration":605,"passed_time":0.8832812737,"remaining_time":0.5742785839},
{"learn":[0.0814430688],"iteration":606,"passed_time":0.8846502051,"remaining_time":0.5727636419},
{"learn":[0.08136198513],"iteration":607,"passed_time":0.8859950398,"remaining_time":0.5712336441},
{"learn":[0.08128411145],"iteration":608,"passed_time":0.8872745691,"remaining_time":0.569662326},
{"learn":[0.08115392723],"iteration":609,"passed_time":0.8887223636,"remaining_time":0.5681995439},
{"learn":[0.0810781539],"iteration":610,"passed_time":0.8900106747,"remaining_time":0.5666352741},
{"learn":[0.08101563638],"iteration":611,"passed_time":0.8913007067,"remaining_time":0.565072997},
{"learn":[0.08094225811],"iteration":612,"passed_time":0.8925777926,"remaining_time":0.5635034351},
{"learn":[0.08081167986],"iteration":613,"passed_time":0.8939689318,"remaining_time":0.5620065271},
{"learn":[0.08063390765],"iteration":614,"passed_time":0.8953374168,"remaining_time":0.5604957812},
{"learn":[0.08059961132],"iteration":615,"passed_time":0.8966974185,"remaining_time":0.5589802089},
{"learn":[0.08054733423],"iteration":616,"passed_time":0.8980512864,"remaining_time":0.5574613334},
{"learn":[0.08045313969],"iteration":617,"passed_time":0.8993799058,"remaining_time":0.5559273851},
{"learn":[0.0801674687],"iteration":618,"passed_time":0.9007883658,"remaining_time":0.5544432429},
{"learn":[0.0800361139],"iteration":619,"passed_time":0.9021091454,"remaining_time":0.5529056053},
{"learn":[0.07999569957],"iteration":620,"passed_time":0.9034910408,"remaining_time":0.5514059653},
{"learn":[0.07993624424],"iteration":621,"passed_time":0.9049708738,"remaining_time":0.5499662223},
{"learn":[0.07965082139],"iteration":622,"passed_time":0.9064232343,"remaining_time":0.5485097261},
{"learn":[0.07952991107],"iteration":623,"passed_time":0.9077923034,"remaining_time":0.5470030546},
{"learn":[0.07947448641],"iteration":624,"passed_time":0.9091496035,"remaining_time":0.5454897621},
{"learn":[0.07931260713],"iteration":625,"passed_time":0.9105365836,"remaining_time":0.5439947001},
{"learn":[0.07895182121],"iteration":626,"passed_time":0.9119024489,"remaining_time":0.5424874217},
{"learn":[0.07873325007],"iteration":627,"passed_time":0.9134028832,"remaining_time":0.5410603066},
{"learn":[0.07865255923],"iteration":628,"passed_time":0.9147805309,"remaining_time":0.5395605357},
{"learn":[0.07850559495],"iteration":629,"passed_time":0.9161343557,"remaining_time":0.5380471613},
{"learn":[0.07838964043],"iteration":630,"passed_time":0.917469454,"remaining_time":0.5365233416},
{"learn":[0.07808925085],"iteration":631,"passed_time":0.9188039326,"remaining_time":0.5349997582},
{"learn":[0.07804342917],"iteration":632,"passed_time":0.9201377833,"remaining_time":0.5334764083},
{"learn":[0.07791335861],"iteration":633,"passed_time":0.9214717493,"remaining_time":0.5319537228},
{"learn":[0.07778319201],"iteration":634,"passed_time":0.9227800776,"remaining_time":0.530416895},
{"learn":[0.07762734687],"iteration":635,"passed_time":0.92415182,"remaining_time":0.5289170794},
{"learn":[0.07755082972],"iteration":636,"passed_time":0.9254791745,"remaining_time":0.527392371},
{"learn":[0.07736630781],"iteration":637,"passed_time":0.9268112722,"remaining_time":0.5258709727},
{"learn":[0.07723596453],"iteration":638,"passed_time":0.9282036368,"remaining_time":0.5243842142},
{"learn":[0.07715044678],"iteration":639,"passed_time":0.9297641088,"remaining_time":0.5229923112},
{"learn":[0.07707465802],"iteration":640,"passed_time":0.9317941737,"remaining_time":0.5218628835},
{"learn":[0.07694213578],"iteration":641,"passed_time":0.9336512887,"remaining_time":0.5206342077},
{"learn":[0.07680284961],"iteration":642,"passed_time":0.9356618159,"remaining_time":0.5194887531},
{"learn":[0.07655023273],"iteration":643,"passed_time":0.9375466198,"remaining_time":0.5182711128},
{"learn":[0.07646605598],"iteration":644,"passed_time":0.9395143714,"remaining_time":0.5170970571},
{"learn":[0.07621911626],"iteration":645,"passed_time":0.9414921644,"remaining_time":0.5159260468},
{"learn":[0.07609049897],"iteration":646,"passed_time":0.9434806253,"remaining_time":0.5147583628},
{"learn":[0.07598685174],"iteration":647,"passed_time":0.9453613557,"remaining_time":0.5135296253},
{"learn":[0.07589979274],"iteration":648,"passed_time":0.9471945108,"remaining_time":0.5122731484},
{"learn":[0.07562209618],"iteration":649,"passed_time":0.9492912107,"remaining_time":0.5111568058},
{"learn":[0.07542265484],"iteration":650,"passed_time":0.9506661152,"remaining_time":0.509650498},
{"learn":[0.07534094983],"iteration":651,"passed_time":0.952000012,"remaining_time":0.5081227058},
{"learn":[0.07513421201],"iteration":652,"passed_time":0.9533645254,"remaining_time":0.5066117769},
{"learn":[0.07499405896],"iteration":653,"passed_time":0.9547183896,"remaining_time":0.5050956618},
{"learn":[0.07492796628],"iteration":654,"passed_time":0.9561166372,"remaining_time":0.5036034196},
{"learn":[0.07483165667],"iteration":655,"passed_time":0.9576043888,"remaining_time":0.502158399},
{"learn":[0.07473060191],"iteration":656,"passed_time":0.9590378831,"remaining_time":0.5006849222},
{"learn":[0.07460618666],"iteration":657,"passed_time":0.9606976006,"remaining_time":0.4993291481},
{"learn":[0.07454753908],"iteration":658,"passed_time":0.9625056196,"remaining_time":0.4980491901},
{"learn":[0.0744623471],"iteration":659,"passed_time":0.9642834952,"remaining_time":0.4967521036},
{"learn":[0.07435764019],"iteration":660,"passed_time":0.9658660915,"remaining_time":0.4953534115},
{"learn":[0.07423453185],"iteration":661,"passed_time":0.9675122878,"remaining_time":0.4939866364},
{"learn":[0.07400536704],"iteration":662,"passed_time":0.9692695821,"remaining_time":0.492675489},
{"learn":[0.07390611527],"iteration":663,"passed_time":0.9710000446,"remaining_time":0.4913494202},
{"learn":[0.07388727519],"iteration":664,"passed_time":0.9725447745,"remaining_time":0.4899285706},
{"learn":[0.07379030231],"iteration":665,"passed_time":0.9741339733,"remaining_time":0.4885296503},
{"learn":[0.07376614486],"iteration":666,"passed_time":0.9758905243,"remaining_time":0.48721371},
{"learn":[0.07368274027],"iteration":667,"passed_time":0.9776031584,"remaining_time":0.4858746236},
{"learn":[0.07364035738],"iteration":668,"passed_time":0.9792190387,"remaining_time":0.4844865498},
{"learn":[0.0734867228],"iteration":669,"passed_time":0.9807962014,"remaining_time":0.4830787261},
{"learn":[0.07303908436],"iteration":670,"passed_time":0.9823380125,"remaining_time":0.4816530642},
{"learn":[0.07290873291],"iteration":671,"passed_time":0.9839646313,"remaining_time":0.480268451},
{"learn":[0.07279586504],"iteration":672,"passed_time":0.9860531524,"remaining_time":0.4791075495},
{"learn":[0.07261270496],"iteration":673,"passed_time":0.9875682872,"remaining_time":0.4776665603},
{"learn":[0.07249712871],"iteration":674,"passed_time":0.9889169648,"remaining_time":0.4761452053},
{"learn":[0.0723675889],"iteration":675,"passed_time":0.9903055772,"remaining_time":0.4746435015},
{"learn":[0.07224687237],"iteration":676,"passed_time":0.9917080947,"remaining_time":0.473148766},
{"learn":[0.07218319915],"iteration":677,"passed_time":0.9930788795,"remaining_time":0.4716392319},
{"learn":[0.07208067043],"iteration":678,"passed_time":0.994472157,"remaining_time":0.4701407399},
{"learn":[0.07201215806],"iteration":679,"passed_time":0.9958357918,"remaining_time":0.4686286079},
{"learn":[0.07188122326],"iteration":680,"passed_time":0.997149207,"remaining_time":0.4670933877},
{"learn":[0.07177596317],"iteration":681,"passed_time":0.9985513882,"remaining_time":0.4656002074},
{"learn":[0.07173893874],"iteration":682,"passed_time":0.999859977,"remaining_time":0.4640638546},
{"learn":[0.07165536835],"iteration":683,"passed_time":1.001274771,"remaining_time":0.4625772333},
{"learn":[0.07157202363],"iteration":684,"passed_time":1.002715322,"remaining_time":0.4611026661},
{"learn":[0.07148752968],"iteration":685,"passed_time":1.004175836,"remaining_time":0.459637336},
{"learn":[0.07130409297],"iteration":686,"passed_time":1.005580496,"remaining_time":0.4581465725},
{"learn":[0.07126350361],"iteration":687,"passed_time":1.006900317,"remaining_time":0.4566175855},
{"learn":[0.07117906511],"iteration":688,"passed_time":1.008270251,"remaining_time":0.455111826},
{"learn":[0.07105077508],"iteration":689,"passed_time":1.00975234,"remaining_time":0.4536568484},
{"learn":[0.0710274895],"iteration":690,"passed_time":1.011240278,"remaining_time":0.4522044081},
{"learn":[0.07095306866],"iteration":691,"passed_time":1.012632179,"remaining_time":0.45070912},
{"learn":[0.07081295829],"iteration":692,"passed_time":1.01402238,"remaining_time":0.4492133777},
{"learn":[0.07064121442],"iteration":693,"passed_time":1.015345963,"remaining_time":0.4476885657},
{"learn":[0.07054458772],"iteration":694,"passed_time":1.016648603,"remaining_time":0.4461551423},
{"learn":[0.07052395858],"iteration":695,"passed_time":1.017691369,"remaining_time":0.4445088739},
{"learn":[0.07051353545],"iteration":696,"passed_time":1.019028552,"remaining_time":0.4429923262},
{"learn":[0.07041556303],"iteration":697,"passed_time":1.020368416,"remaining_time":0.4414774522},
{"learn":[0.07027283918],"iteration":698,"passed_time":1.021754805,"remaining_time":0.4399831133},
{"learn":[0.07016736081],"iteration":699,"passed_time":1.023102571,"remaining_time":0.4384725303},
{"learn":[0.07011907968],"iteration":700,"passed_time":1.024420098,"remaining_time":0.4369495141},
{"learn":[0.07000587844],"iteration":701,"passed_time":1.025846616,"remaining_time":0.4354733497},
{"learn":[0.06991505125],"iteration":702,"passed_time":1.027229402,"remaining_time":0.4339788511},
{"learn":[0.06980581535],"iteration":703,"passed_time":1.028593822,"remaining_time":0.432476948},
{"learn":[0.06964058699],"iteration":704,"passed_time":1.029959004,"remaining_time":0.4309757534},
{"learn":[0.06959051872],"iteration":705,"passed_time":1.0313922,"remaining_time":0.4295032676},
{"learn":[0.06951967216],"iteration":706,"passed_time":1.032859465,"remaining_time":0.4280450118},
{"learn":[0.06937393177],"iteration":707,"passed_time":1.034497233,"remaining_time":0.4266570511},
{"learn":[0.06926328514],"iteration":708,"passed_time":1.036297863,"remaining_time":0.42533523},
{"learn":[0.06914340156],"iteration":709,"passed_time":1.03764252,"remaining_time":0.4238258182},
{"learn":[0.06896594381],"iteration":710,"passed_time":1.039379969,"remaining_time":0.4224765273},
{"learn":[0.06890447271],"iteration":711,"passed_time":1.040923064,"remaining_time":0.4210475314},
{"learn":[0.06879585307],"iteration":712,"passed_time":1.042948401,"remaining_time":0.4198123299},
{"learn":[0.06859456369],"iteration":713,"passed_time":1.044450543,"remaining_time":0.4183653437},
{"learn":[0.06851559729],"iteration":714,"passed_time":1.046082283,"remaining_time":0.4169698612},
{"learn":[0.06837510717],"iteration":715,"passed_time":1.047486983,"remaining_time":0.4154836637},
{"learn":[0.06831420995],"iteration":716,"passed_time":1.048819951,"remaining_time":0.413969381},
{"learn":[0.06817084265],"iteration":717,"passed_time":1.050151266,"remaining_time":0.4124549539},
{"learn":[0.06794628699],"iteration":718,"passed_time":1.051477229,"remaining_time":0.410938945},
{"learn":[0.06787944655],"iteration":719,"passed_time":1.052796476,"remaining_time":0.4094208519},
{"learn":[0.06779627555],"iteration":720,"passed_time":1.054144312,"remaining_time":0.4079143733},
{"learn":[0.06768496691],"iteration":721,"passed_time":1.055494479,"remaining_time":0.4064092315},
{"learn":[0.0676394163],"iteration":722,"passed_time":1.056819732,"remaining_time":0.4048949735},
{"learn":[0.06741699025],"iteration":723,"passed_time":1.05842612,"remaining_time":0.4034884105},
{"learn":[0.06733195496],"iteration":724,"passed_time":1.05977418,"remaining_time":0.4019833095},
{"learn":[0.06723990735],"iteration":725,"passed_time":1.06115135,"remaining_time":0.4004896278},
{"learn":[0.06711419614],"iteration":726,"passed_time":1.062510368,"remaining_time":0.3989894506},
{"learn":[0.06705893806],"iteration":727,"passed_time":1.063805175,"remaining_time":0.3974656697},
{"learn":[0.06697828956],"iteration":728,"passed_time":1.065192941,"remaining_time":0.3959770739},
{"learn":[0.06693613382],"iteration":729,"passed_time":1.066576545,"remaining_time":0.3944872153},
{"learn":[0.06688322236],"iteration":730,"passed_time":1.068059652,"remaining_time":0.3930342631},
{"learn":[0.06673912604],"iteration":731,"passed_time":1.069466005,"remaining_time":0.3915531277},
{"learn":[0.06661890483],"iteration":732,"passed_time":1.070818325,"remaining_time":0.390052514},
{"learn":[0.0664894496],"iteration":733,"passed_time":1.072212697,"remaining_time":0.3885675441},
{"learn":[0.0664351666],"iteration":734,"passed_time":1.073651692,"remaining_time":0.3870989093},
{"learn":[0.0663700921],"iteration":735,"passed_time":1.075253029,"remaining_time":0.3856885866},
{"learn":[0.06624884038],"iteration":736,"passed_time":1.076702786,"remaining_time":0.3842236536},
{"learn":[0.06616967387],"iteration":737,"passed_time":1.078103568,"remaining_time":0.3827413749},
{"learn":[0.06607031002],"iteration":738,"passed_time":1.079516743,"remaining_time":0.3812636942},
{"learn":[0.06601619127],"iteration":739,"passed_time":1.080803087,"remaining_time":0.3797416252},
{"learn":[0.06591733272],"iteration":740,"passed_time":1.082218254,"remaining_time":0.3782652196},
{"learn":[0.0658256997],"iteration":741,"passed_time":1.08355679,"remaining_time":0.3767623338},
{"learn":[0.06571916641],"iteration":742,"passed_time":1.084995232,"remaining_time":0.3752944476},
{"learn":[0.06558992423],"iteration":743,"passed_time":1.08641745,"remaining_time":0.3738210581},
{"learn":[0.06553750841],"iteration":744,"passed_time":1.087779956,"remaining_time":0.3723273676},
{"learn":[0.06546066491],"iteration":745,"passed_time":1.089128054,"remaining_time":0.370829123},
{"learn":[0.06540534616],"iteration":746,"passed_time":1.090507502,"remaining_time":0.3693418982},
{"learn":[0.06529795678],"iteration":747,"passed_time":1.092295265,"remaining_time":0.3679925223},
{"learn":[0.06524652456],"iteration":748,"passed_time":1.093632473,"remaining_time":0.366490989},
{"learn":[0.06504084196],"iteration":749,"passed_time":1.095009968,"remaining_time":0.3650033228},
{"learn":[0.06493994989],"iteration":750,"passed_time":1.096353488,"remaining_time":0.363504685},
{"learn":[0.06483122234],"iteration":751,"passed_time":1.097685046,"remaining_time":0.3620025151},
{"learn":[0.06471206759],"iteration":752,"passed_time":1.099051862,"remaining_time":0.3605123638},
{"learn":[0.06453459977],"iteration":753,"passed_time":1.100497059,"remaining_time":0.3590481121},
{"learn":[0.0644616617],"iteration":754,"passed_time":1.102659926,"remaining_time":0.357816797},
{"learn":[0.06430568277],"iteration":755,"passed_time":1.104087801,"remaining_time":0.3563457982},
{"learn":[0.06422041288],"iteration":756,"passed_time":1.105468813,"remaining_time":0.35485987},
{"learn":[0.06415131637],"iteration":757,"passed_time":1.106851471,"remaining_time":0.3533747441},
{"learn":[0.06406465311],"iteration":758,"passed_time":1.108357466,"remaining_time":0.3519290506},
{"learn":[0.06390231428],"iteration":759,"passed_time":1.109745754,"remaining_time":0.3504460277},
{"learn":[0.06381941168],"iteration":760,"passed_time":1.111065001,"remaining_time":0.3489415705},
{"learn":[0.06375149851],"iteration":761,"passed_time":1.112362931,"remaining_time":0.3474309417},
{"learn":[0.0636944269],"iteration":762,"passed_time":1.113678068,"remaining_time":0.3459262151},
{"learn":[0.06362040903],"iteration":763,"passed_time":1.114974932,"remaining_time":0.3444163404},
{"learn":[0.06351708822],"iteration":764,"passed_time":1.116344717,"remaining_time":0.3429294229},
{"learn":[0.06337794091],"iteration":765,"passed_time":1.117633978,"remaining_time":0.3414182125},
{"learn":[0.0632531839],"iteration":766,"passed_time":1.118898309,"remaining_time":0.3399000078},
{"learn":[0.06320391698],"iteration":767,"passed_time":1.120217094,"remaining_time":0.3383989137},
{"learn":[0.06315655015],"iteration":768,"passed_time":1.121537395,"remaining_time":0.3368987493},
{"learn":[0.06299788979],"iteration":769,"passed_time":1.122841354,"remaining_time":0.3353941705},
{"learn":[0.06293426787],"iteration":770,"passed_time":1.124129374,"remaining_time":0.3338853782},
{"learn":[0.06286721267],"iteration":771,"passed_time":1.125627522,"remaining_time":0.3324392164},
{"learn":[0.0628029536],"iteration":772,"passed_time":1.127063331,"remaining_time":0.3309746135},
{"learn":[0.06273049159],"iteration":773,"passed_time":1.128616483,"remaining_time":0.3295443477},
{"learn":[0.06268584001],"iteration":774,"passed_time":1.130310795,"remaining_time":0.3281547468},
{"learn":[0.06263198752],"iteration":775,"passed_time":1.131685268,"remaining_time":0.3266720362},
{"learn":[0.0625287821],"iteration":776,"passed_time":1.133015155,"remaining_time":0.3251768078},
{"learn":[0.06241137113],"iteration":777,"passed_time":1.134484371,"remaining_time":0.3237217614},
{"learn":[0.06226484982],"iteration":778,"passed_time":1.135977288,"remaining_time":0.3222734026},
{"learn":[0.06218949327],"iteration":779,"passed_time":1.13737373,"remaining_time":0.3207977188},
{"learn":[0.06214158769],"iteration":780,"passed_time":1.139149832,"remaining_time":0.3194286981},
{"learn":[0.06207635668],"iteration":781,"passed_time":1.141044269,"remaining_time":0.3180916249},
{"learn":[0.06201963266],"iteration":782,"passed_time":1.142569295,"remaining_time":0.3166507496},
{"learn":[0.06184402274],"iteration":783,"passed_time":1.144130361,"remaining_time":0.3152195891},
{"learn":[0.0617752493],"iteration":784,"passed_time":1.145468207,"remaining_time":0.3137269612},
{"learn":[0.06170555057],"iteration":785,"passed_time":1.14680678,"remaining_time":0.3122349249},
{"learn":[0.06159963498],"iteration":786,"passed_time":1.148212307,"remaining_time":0.3107613996},
{"learn":[0.06140017415],"iteration":787,"passed_time":1.149529449,"remaining_time":0.3092642681},
{"learn":[0.06132380893],"iteration":788,"passed_time":1.150801274,"remaining_time":0.3077554737},
{"learn":[0.06124085216],"iteration":789,"passed_time":1.152115615,"remaining_time":0.3062585813},
{"learn":[0.06109963178],"iteration":790,"passed_time":1.153463055,"remaining_time":0.3047708956},
{"learn":[0.06105160944],"iteration":791,"passed_time":1.154765877,"remaining_time":0.3032718464},
{"learn":[0.06092631689],"iteration":792,"passed_time":1.156064521,"remaining_time":0.3017722017},
{"learn":[0.0608179371],"iteration":793,"passed_time":1.157370068,"remaining_time":0.3002748539},
{"learn":[0.06076955214],"iteration":794,"passed_time":1.158683447,"remaining_time":0.2987800082},
{"learn":[0.06053016603],"iteration":795,"passed_time":1.160026246,"remaining_time":0.2972931586},
{"learn":[0.06042281411],"iteration":796,"passed_time":1.16142111,"remaining_time":0.2958199314},
{"learn":[0.06039352619],"iteration":797,"passed_time":1.1627599,"remaining_time":0.2943327066},
{"learn":[0.06030426352],"iteration":798,"passed_time":1.164102833,"remaining_time":0.2928468955},
{"learn":[0.06027594593],"iteration":799,"passed_time":1.165482451,"remaining_time":0.2913706128},
{"learn":[0.06023213933],"iteration":800,"passed_time":1.166931574,"remaining_time":0.2899118394},
{"learn":[0.0601471797],"iteration":801,"passed_time":1.168359154,"remaining_time":0.2884477711},
{"learn":[0.06004348615],"iteration":802,"passed_time":1.169714551,"remaining_time":0.2869660855},
{"learn":[0.0599814411],"iteration":803,"passed_time":1.171069253,"remaining_time":0.2854845444},
{"learn":[0.05991777566],"iteration":804,"passed_time":1.17234804,"remaining_time":0.283984929},
{"learn":[0.05981493222],"iteration":805,"passed_time":1.173747841,"remaining_time":0.2825149889},
{"learn":[0.05974943482],"iteration":806,"passed_time":1.175146897,"remaining_time":0.2810450447},
{"learn":[0.05966961102],"iteration":807,"passed_time":1.176659882,"remaining_time":0.2796023482},
{"learn":[0.05963970016],"iteration":808,"passed_time":1.178043899,"remaining_time":0.2781290294},
{"learn":[0.05958108019],"iteration":809,"passed_time":1.179259922,"remaining_time":0.2766165248},
{"learn":[0.05948776308],"iteration":810,"passed_time":1.180604486,"remaining_time":0.2751347077},
{"learn":[0.05941464488],"iteration":811,"passed_time":1.182088092,"remaining_time":0.2736854204},
{"learn":[0.05934518526],"iteration":812,"passed_time":1.183469247,"remaining_time":0.2722124835},
{"learn":[0.05925239925],"iteration":813,"passed_time":1.184770624,"remaining_time":0.2707215431},
{"learn":[0.05923403479],"iteration":814,"passed_time":1.186074587,"remaining_time":0.2692316548},
{"learn":[0.05907460952],"iteration":815,"passed_time":1.187401939,"remaining_time":0.267747496},
{"learn":[0.05880875485],"iteration":816,"passed_time":1.18877391,"remaining_time":0.2662737156},
{"learn":[0.05871371528],"iteration":817,"passed_time":1.190097678,"remaining_time":0.2647894589},
{"learn":[0.05868108015],"iteration":818,"passed_time":1.191428576,"remaining_time":0.26330717},
{"learn":[0.0585331975],"iteration":819,"passed_time":1.192752642,"remaining_time":0.2618237506},
{"learn":[0.05850859797],"iteration":820,"passed_time":1.194065322,"remaining_time":0.260338237},
{"learn":[0.05833260762],"iteration":821,"passed_time":1.195447088,"remaining_time":0.2588681043},
{"learn":[0.05824304981],"iteration":822,"passed_time":1.196751196,"remaining_time":0.2573814844},
{"learn":[0.05809856196],"iteration":823,"passed_time":1.19823094,"remaining_time":0.255932822},
{"learn":[0.05796593536],"iteration":824,"passed_time":1.199604863,"remaining_time":0.2544616377},
{"learn":[0.0579018494],"iteration":825,"passed_time":1.200915117,"remaining_time":0.2529772764},
{"learn":[0.05783896569],"iteration":826,"passed_time":1.202191891,"remaining_time":0.2514863328},
{"learn":[0.05774267274],"iteration":827,"passed_time":1.203553116,"remaining_time":0.2500134491},
{"learn":[0.05761894433],"iteration":828,"passed_time":1.204896325,"remaining_time":0.2485371188},
{"learn":[0.05757597546],"iteration":829,"passed_time":1.206353758,"remaining_time":0.2470845046},
{"learn":[0.05754274285],"iteration":830,"passed_time":1.207806708,"remaining_time":0.245630967},
{"learn":[0.05746457353],"iteration":831,"passed_time":1.209167875,"remaining_time":0.2441588979},
{"learn":[0.0574081862],"iteration":832,"passed_time":1.210485353,"remaining_time":0.2426783361},
{"learn":[0.05737294514],"iteration":833,"passed_time":1.211890329,"remaining_time":0.2412155812},
{"learn":[0.05733224032],"iteration":834,"passed_time":1.213481614,"remaining_time":0.2397897801},
{"learn":[0.05728313136],"iteration":835,"passed_time":1.214926618,"remaining_time":0.2383348868},
{"learn":[0.05718115653],"iteration":836,"passed_time":1.216303694,"remaining_time":0.2368667886},
{"learn":[0.05713633583],"iteration":837,"passed_time":1.217666049,"remaining_time":0.2353960621},
{"learn":[0.05709468386],"iteration":838,"passed_time":1.219002752,"remaining_time":0.2339206711},
{"learn":[0.05705938948],"iteration":839,"passed_time":1.220287191,"remaining_time":0.2324356554},
{"learn":[0.0569671509],"iteration":840,"passed_time":1.221651472,"remaining_time":0.2309662118},
{"learn":[0.05690282704],"iteration":841,"passed_time":1.223059697,"remaining_time":0.2295052637},
{"learn":[0.0568860206],"iteration":842,"passed_time":1.224333802,"remaining_time":0.2280194625},
{"learn":[0.05684427723],"iteration":843,"passed_time":1.225635228,"remaining_time":0.2265392127},
{"learn":[0.05676778392],"iteration":844,"passed_time":1.227046474,"remaining_time":0.2250795307},
{"learn":[0.05657421336],"iteration":845,"passed_time":1.228482701,"remaining_time":0.2236245107},
{"learn":[0.0565067099],"iteration":846,"passed_time":1.229833856,"remaining_time":0.2221541676},
{"learn":[0.05642192142],"iteration":847,"passed_time":1.231226962,"remaining_time":0.2206916252},
{"learn":[0.0563729164],"iteration":848,"passed_time":1.232536221,"remaining_time":0.2192143338},
{"learn":[0.05631592946],"iteration":849,"passed_time":1.233951825,"remaining_time":0.2177562044},
{"learn":[0.05623716073],"iteration":850,"passed_time":1.235314315,"remaining_time":0.2162888753},
{"learn":[0.05613822433],"iteration":851,"passed_time":1.23668397,"remaining_time":0.214823037},
{"learn":[0.05605015393],"iteration":852,"passed_time":1.238342906,"remaining_time":0.2134072769},
{"learn":[0.05602670133],"iteration":853,"passed_time":1.240053492,"remaining_time":0.2119997773},
{"learn":[0.05596661475],"iteration":854,"passed_time":1.241423136,"remaining_time":0.2105337481},
{"learn":[0.0559368236],"iteration":855,"passed_time":1.242822923,"remaining_time":0.209073015},
{"learn":[0.05586733763],"iteration":856,"passed_time":1.244161681,"remaining_time":0.2076022408},
{"learn":[0.0557860777],"iteration":857,"passed_time":1.245513117,"remaining_time":0.2061338725},
{"learn":[0.0557024388],"iteration":858,"passed_time":1.246926537,"remaining_time":0.2046759508},
{"learn":[0.05560342198],"iteration":859,"passed_time":1.248562293,"remaining_time":0.2032543268},
{"learn":[0.05553382244],"iteration":860,"passed_time":1.249944103,"remaining_time":0.2017912083},
{"learn":[0.05546435415],"iteration":861,"passed_time":1.25127709,"remaining_time":0.2003204622},
{"learn":[0.05542359496],"iteration":862,"passed_time":1.252655746,"remaining_time":0.1988572853},
{"learn":[0.05538226528],"iteration":863,"passed_time":1.254199145,"remaining_time":0.1974202358},
{"learn":[0.05532543218],"iteration":864,"passed_time":1.255645884,"remaining_time":0.1959678547},
{"learn":[0.05525163127],"iteration":865,"passed_time":1.257045176,"remaining_time":0.194508145},
{"learn":[0.05520753258],"iteration":866,"passed_time":1.258645409,"remaining_time":0.1930793996},
{"learn":[0.05516273442],"iteration":867,"passed_time":1.260228672,"remaining_time":0.1916476782},
{"learn":[0.05510319203],"iteration":868,"passed_time":1.261784219,"remaining_time":0.19021143},
{"learn":[0.05500133328],"iteration":869,"passed_time":1.26317184,"remaining_time":0.1887498152},
{"learn":[0.05489121915],"iteration":870,"passed_time":1.264627715,"remaining_time":0.187298479},
{"learn":[0.05481172637],"iteration":871,"passed_time":1.265979301,"remaining_time":0.185831824},
{"learn":[0.05472539783],"iteration":872,"passed_time":1.267398805,"remaining_time":0.184375313},
{"learn":[0.05460081326],"iteration":873,"passed_time":1.268811577,"remaining_time":0.1829179161},
{"learn":[0.05452509413],"iteration":874,"passed_time":1.27021717,"remaining_time":0.1814595956},
{"learn":[0.05446612774],"iteration":875,"passed_time":1.271781556,"remaining_time":0.1800238732},
{"learn":[0.05443223605],"iteration":876,"passed_time":1.273088374,"remaining_time":0.1785517332},
{"learn":[0.05439924906],"iteration":877,"passed_time":1.274544005,"remaining_time":0.1771006476},
{"learn":[0.0543273772],"iteration":878,"passed_time":1.275921244,"remaining_time":0.1756387606},
{"learn":[0.05422304831],"iteration":879,"passed_time":1.277258403,"remaining_time":0.1741716004},
{"learn":[0.05415005396],"iteration":880,"passed_time":1.278594117,"remaining_time":0.1727045402},
{"learn":[0.05410922604],"iteration":881,"passed_time":1.27994817,"remaining_time":0.1712402313},
{"learn":[0.05403175516],"iteration":882,"passed_time":1.281269778,"remaining_time":0.1697718732},
{"learn":[0.05391741394],"iteration":883,"passed_time":1.28271267,"remaining_time":0.1683197622},
{"learn":[0.05386813253],"iteration":884,"passed_time":1.283987872,"remaining_time":0.1668458816},
{"learn":[0.05376847803],"iteration":885,"passed_time":1.285357677,"remaining_time":0.165384622},
{"learn":[0.05368164265],"iteration":886,"passed_time":1.286738552,"remaining_time":0.163924979},
{"learn":[0.05357091273],"iteration":887,"passed_time":1.288120816,"remaining_time":0.1624656884},
{"learn":[0.05344351992],"iteration":888,"passed_time":1.289504107,"remaining_time":0.1610066996},
{"learn":[0.05340996016],"iteration":889,"passed_time":1.290866777,"remaining_time":0.159545332},
{"learn":[0.05336432283],"iteration":890,"passed_time":1.29221634,"remaining_time":0.1580825826},
{"learn":[0.05331100814],"iteration":891,"passed_time":1.293624799,"remaining_time":0.1566272179},
{"learn":[0.05325631075],"iteration":892,"passed_time":1.29529031,"remaining_time":0.1552027583},
{"learn":[0.05318236395],"iteration":893,"passed_time":1.296725641,"remaining_time":0.1537504674},
{"learn":[0.05314943634],"iteration":894,"passed_time":1.298143593,"remaining_time":0.1522961757},
{"learn":[0.0531130759],"iteration":895,"passed_time":1.299495276,"remaining_time":0.1508342731},
{"learn":[0.05303387951],"iteration":896,"passed_time":1.300929643,"remaining_time":0.1493821106},
{"learn":[0.05285737191],"iteration":897,"passed_time":1.302349903,"remaining_time":0.1479283854},
{"learn":[0.05257233533],"iteration":898,"passed_time":1.303810765,"remaining_time":0.1464792962},
{"learn":[0.05250628579],"iteration":899,"passed_time":1.305235741,"remaining_time":0.1450261935},
{"learn":[0.05243175397],"iteration":900,"passed_time":1.306621332,"remaining_time":0.1435688256},
{"learn":[0.05241006242],"iteration":901,"passed_time":1.307990875,"remaining_time":0.1421098734},
{"learn":[0.05235323319],"iteration":902,"passed_time":1.309317481,"remaining_time":0.1406465069},
{"learn":[0.05228637803],"iteration":903,"passed_time":1.310660247,"remaining_time":0.139185159},
{"learn":[0.05223665667],"iteration":904,"passed_time":1.311996636,"remaining_time":0.1377234037},
{"learn":[0.05218119913],"iteration":905,"passed_time":1.313335993,"remaining_time":0.1362622332},
{"learn":[0.05212773487],"iteration":906,"passed_time":1.314659883,"remaining_time":0.1347997455},
{"learn":[0.05203402402],"iteration":907,"passed_time":1.316017903,"remaining_time":0.133341021},
{"learn":[0.05199519641],"iteration":908,"passed_time":1.317377918,"remaining_time":0.1318827178},
{"learn":[0.05193059223],"iteration":909,"passed_time":1.318707565,"remaining_time":0.1304216273},
{"learn":[0.05187002699],"iteration":910,"passed_time":1.320159049,"remaining_time":0.1289727282},
{"learn":[0.0518511145],"iteration":911,"passed_time":1.321997592,"remaining_time":0.1275611712},
{"learn":[0.05178301373],"iteration":912,"passed_time":1.323558657,"remaining_time":0.1261222379},
{"learn":[0.05171306132],"iteration":913,"passed_time":1.324977786,"remaining_time":0.1246696823},
{"learn":[0.05169086573],"iteration":914,"passed_time":1.326321751,"remaining_time":0.1232102173},
{"learn":[0.05163764831],"iteration":915,"passed_time":1.32764499,"remaining_time":0.1217491039},
{"learn":[0.05151203162],"iteration":916,"passed_time":1.32905759,"remaining_time":0.1202963794},
{"learn":[0.05144698479],"iteration":917,"passed_time":1.330520149,"remaining_time":0.118848205},
{"learn":[0.0513786135],"iteration":918,"passed_time":1.332012736,"remaining_time":0.1174026459},
{"learn":[0.05134399256],"iteration":919,"passed_time":1.333422432,"remaining_time":0.1159497767},
{"learn":[0.05129678813],"iteration":920,"passed_time":1.334897611,"remaining_time":0.1145026181},
{"learn":[0.05125324084],"iteration":921,"passed_time":1.33637167,"remaining_time":0.113055304},
{"learn":[0.05121482396],"iteration":922,"passed_time":1.33779459,"remaining_time":0.1116036657},
{"learn":[0.05115485566],"iteration":923,"passed_time":1.339255629,"remaining_time":0.1101552249},
{"learn":[0.05110757236],"iteration":924,"passed_time":1.340642018,"remaining_time":0.1087007041},
{"learn":[0.05102742265],"iteration":925,"passed_time":1.342015811,"remaining_time":0.107245324},
{"learn":[0.05096638145],"iteration":926,"passed_time":1.343440199,"remaining_time":0.1057941042},
{"learn":[0.05089853807],"iteration":927,"passed_time":1.344863885,"remaining_time":0.1043428877},
{"learn":[0.05079680575],"iteration":928,"passed_time":1.346465638,"remaining_time":0.1029053394},
{"learn":[0.05075830465],"iteration":929,"passed_time":1.347846701,"remaining_time":0.1014508269},
{"learn":[0.05071555727],"iteration":930,"passed_time":1.349200232,"remaining_time":0.09999443178},
{"learn":[0.05063001132],"iteration":931,"passed_time":1.35057356,"remaining_time":0.09853970177},
{"learn":[0.05054959465],"iteration":932,"passed_time":1.352179003,"remaining_time":0.09710181477},
{"learn":[0.05043430088],"iteration":933,"passed_time":1.353598095,"remaining_time":0.09565040071},
{"learn":[0.05038997367],"iteration":934,"passed_time":1.355050677,"remaining_time":0.09420138397},
{"learn":[0.05026013707],"iteration":935,"passed_time":1.356414129,"remaining_time":0.09274626522},
{"learn":[0.05021272778],"iteration":936,"passed_time":1.357742607,"remaining_time":0.09128899065},
{"learn":[0.05016591776],"iteration":937,"passed_time":1.359109016,"remaining_time":0.08983449787},
{"learn":[0.05015417887],"iteration":938,"passed_time":1.360434744,"remaining_time":0.08837754994},
{"learn":[0.05007420893],"iteration":939,"passed_time":1.362136905,"remaining_time":0.08694490886},
{"learn":[0.05002615153],"iteration":940,"passed_time":1.363773762,"remaining_time":0.08550760039},
{"learn":[0.04996444715],"iteration":941,"passed_time":1.365431355,"remaining_time":0.08407114498},
{"learn":[0.04993598016],"iteration":942,"passed_time":1.366854388,"remaining_time":0.08262004254},
{"learn":[0.04988125715],"iteration":943,"passed_time":1.368262613,"remaining_time":0.08116812111},
{"learn":[0.04976597303],"iteration":944,"passed_time":1.369760059,"remaining_time":0.07972148493},
{"learn":[0.04969752954],"iteration":945,"passed_time":1.371104593,"remaining_time":0.07826601273},
{"learn":[0.04956289664],"iteration":946,"passed_time":1.372471447,"remaining_time":0.07681202399},
{"learn":[0.04952804046],"iteration":947,"passed_time":1.373834403,"remaining_time":0.07535800522},
{"learn":[0.04949481902],"iteration":948,"passed_time":1.375156819,"remaining_time":0.07390199974},
{"learn":[0.0494320513],"iteration":949,"passed_time":1.376557688,"remaining_time":0.07245040464},
{"learn":[0.049373178],"iteration":950,"passed_time":1.378013113,"remaining_time":0.07100172715},
{"learn":[0.04933270749],"iteration":951,"passed_time":1.379509825,"remaining_time":0.06955511724},
{"learn":[0.0493195949],"iteration":952,"passed_time":1.380807906,"remaining_time":0.06809860607},
{"learn":[0.04926894965],"iteration":953,"passed_time":1.382120058,"remaining_time":0.06664310552},
{"learn":[0.04923237176],"iteration":954,"passed_time":1.383509943,"remaining_time":0.06519156802},
{"learn":[0.04913327159],"iteration":955,"passed_time":1.384880244,"remaining_time":0.06373925809},
{"learn":[0.04906388942],"iteration":956,"passed_time":1.386229288,"remaining_time":0.06228616447},
{"learn":[0.04900947419],"iteration":957,"passed_time":1.391931557,"remaining_time":0.06102413922},
{"learn":[0.04895434742],"iteration":958,"passed_time":1.393482953,"remaining_time":0.05957539215},
{"learn":[0.048874102],"iteration":959,"passed_time":1.395161333,"remaining_time":0.0581317222},
{"learn":[0.04880383518],"iteration":960,"passed_time":1.396802378,"remaining_time":0.05668604865},
{"learn":[0.04871776496],"iteration":961,"passed_time":1.398781229,"remaining_time":0.05525331257},
{"learn":[0.04863788773],"iteration":962,"passed_time":1.400486471,"remaining_time":0.05380892983},
{"learn":[0.04861806538],"iteration":963,"passed_time":1.402040895,"remaining_time":0.05235837369},
{"learn":[0.04856753657],"iteration":964,"passed_time":1.403419905,"remaining_time":0.05090124009},
{"learn":[0.04838929184],"iteration":965,"passed_time":1.404799092,"remaining_time":0.04944427445},
{"learn":[0.04835814582],"iteration":966,"passed_time":1.406117432,"remaining_time":0.04798539322},
{"learn":[0.04832103898],"iteration":967,"passed_time":1.407539193,"remaining_time":0.04653022125},
{"learn":[0.0482772324],"iteration":968,"passed_time":1.408880095,"remaining_time":0.0450725314},
{"learn":[0.04824018317],"iteration":969,"passed_time":1.410330675,"remaining_time":0.0436184745},
{"learn":[0.04818604757],"iteration":970,"passed_time":1.411677395,"remaining_time":0.04216132283},
{"learn":[0.04812525073],"iteration":971,"passed_time":1.413114001,"remaining_time":0.04070698769},
{"learn":[0.04798458682],"iteration":972,"passed_time":1.414616892,"remaining_time":0.03925452834},
{"learn":[0.04793112505],"iteration":973,"passed_time":1.415930162,"remaining_time":0.0377969037},
{"learn":[0.04790055298],"iteration":974,"passed_time":1.417301458,"remaining_time":0.03634106302},
{"learn":[0.04782780266],"iteration":975,"passed_time":1.418704471,"remaining_time":0.03488617551},
{"learn":[0.04777058195],"iteration":976,"passed_time":1.420055024,"remaining_time":0.03343015921},
{"learn":[0.04772070173],"iteration":977,"passed_time":1.421444937,"remaining_time":0.03197524398},
{"learn":[0.04768567341],"iteration":978,"passed_time":1.42275524,"remaining_time":0.03051875387},
{"learn":[0.04758504456],"iteration":979,"passed_time":1.424182565,"remaining_time":0.0290649503},
{"learn":[0.04747443157],"iteration":980,"passed_time":1.426217276,"remaining_time":0.02762296457},
{"learn":[0.0474162123],"iteration":981,"passed_time":1.427604372,"remaining_time":0.02616790091},
{"learn":[0.04731459157],"iteration":982,"passed_time":1.429067327,"remaining_time":0.02471428745},
{"learn":[0.04729074194],"iteration":983,"passed_time":1.430393605,"remaining_time":0.02325843259},
{"learn":[0.04725057896],"iteration":984,"passed_time":1.431930988,"remaining_time":0.02180605565},
{"learn":[0.04722169704],"iteration":985,"passed_time":1.433683562,"remaining_time":0.02035656173},
{"learn":[0.04717819308],"iteration":986,"passed_time":1.435072237,"remaining_time":0.01890166067},
{"learn":[0.04713246241],"iteration":987,"passed_time":1.436478942,"remaining_time":0.01744711266},
{"learn":[0.04707983199],"iteration":988,"passed_time":1.437843118,"remaining_time":0.01599218837},
{"learn":[0.04699463143],"iteration":989,"passed_time":1.439216291,"remaining_time":0.01453753829},
{"learn":[0.04695506584],"iteration":990,"passed_time":1.440535276,"remaining_time":0.01308256053},
{"learn":[0.04688059418],"iteration":991,"passed_time":1.442002809,"remaining_time":0.01162905491},
{"learn":[0.04680680515],"iteration":992,"passed_time":1.44346426,"remaining_time":0.01017547816},
{"learn":[0.04667864177],"iteration":993,"passed_time":1.444925582,"remaining_time":0.0087218848},
{"learn":[0.04662515382],"iteration":994,"passed_time":1.446303829,"remaining_time":0.007267858439},
{"learn":[0.04657611245],"iteration":995,"passed_time":1.447697631,"remaining_time":0.005814046709},
{"learn":[0.04654367428],"iteration":996,"passed_time":1.449090058,"remaining_time":0.004360351226},
{"learn":[0.04648985019],"iteration":997,"passed_time":1.450506979,"remaining_time":0.002906827613},
{"learn":[0.04647382274],"iteration":998,"passed_time":1.452007002,"remaining_time":0.001453460463},
{"learn":[0.046449361],"iteration":999,"passed_time":1.453426443,"remaining_time":0}
]}